{
  "condition_id": 17,
  "total_uses": 45,
  "uses_by_subsystem": {
    "SkillConditionList": 45
  },
  "uses_by_table": {
    "SkillConditionList": 45
  },
  "uses_by_subsystem_slot": {
    "SkillConditionList[0]": 44,
    "SkillConditionList[1]": 1
  },
  "param_stats": {
    "count": 45,
    "min": 0,
    "max": 100,
    "mean": 44.28888888888889,
    "median": 30,
    "p10": 30,
    "p25": 30,
    "p75": 60,
    "p90": 81,
    "top10": [
      [
        30,
        26
      ],
      [
        60,
        10
      ],
      [
        100,
        3
      ],
      [
        81,
        3
      ],
      [
        50,
        1
      ],
      [
        20,
        1
      ],
      [
        0,
        1
      ]
    ]
  },
  "filter_histograms": {
    "ailment_type": [],
    "status_type": [],
    "weapon_type": [],
    "magic_type": [],
    "equipment": []
  },
  "cooccurrence_top": [
    [
      18,
      1
    ],
    [
      10724,
      1
    ]
  ],
  "top_enemies": [],
  "top_skills": {
    "611288": {
      "skill_id": 611288,
      "use_count": 4,
      "name_id": 102724,
      "name_best": "ルカニ",
      "detail_id": 102740,
      "detail_best": "<skl_target_type>に<skl_ailment_status><skl_ailment_value>％と\n物理耐性ダウン<skl_ailment_value2>％の効果を付与(<skl_turn_count>)\n効果対象に対象のHPに応じた効果を付与\n60％以下:<skl_ailment_status2><skl_ailment_value3>％と属性耐性ダウン<skl_ailment_value4>％(<skl_turn_count3>)\n30％以下:さらに、杖・風耐性ダウン<skl_ailment_value5>％(<skl_turn_count5>)",
      "enemies_that_can_use_skill_count": 0,
      "enemies_that_can_use_skill_sample": [],
      "avails": [
        176612,
        176613,
        176614,
        176615,
        176616,
        176617
      ]
    },
    "52089": {
      "skill_id": 52089,
      "use_count": 3,
      "name_id": 96453,
      "name_best": "絶望の連鎖",
      "detail_id": 96498,
      "detail_best": "味方前後衛全体に対象のHPに応じた効果を付与(<skl_turn_count>)\nHP50％以下の時：同対象に物攻・属攻アップ<skl_ailment_value>％\nHP20％以下の時：さらに、ダメージアップ<skl_ailment_value2>％\nその後、同対象のHP回復(効力 <skl_avail_value>)",
      "enemies_that_can_use_skill_count": 0,
      "enemies_that_can_use_skill_sample": [],
      "avails": [
        9984,
        9985,
        9975
      ]
    },
    "612638": {
      "skill_id": 612638,
      "use_count": 3,
      "name_id": 104291,
      "name_best": "瘴気が深くなる……",
      "detail_id": 0,
      "detail_best": "no data.",
      "enemies_that_can_use_skill_count": 0,
      "enemies_that_can_use_skill_sample": [],
      "avails": [
        79119,
        79120,
        79121,
        79122,
        79123,
        79124,
        79125,
        79126,
        79127,
        79128,
        79113,
        79338,
        79339,
        79340
      ]
    },
    "611286": {
      "skill_id": 611286,
      "use_count": 2,
      "name_id": 102722,
      "name_best": "バギ",
      "detail_id": 102738,
      "detail_best": "<skl_target_type>に2回の<skl_attribute_name><skl_calc_type>攻撃(威力 <skl_avail_value>)\n攻撃対象毎に対象のHPに応じて攻撃回数が変化\n60％以下:攻撃回数が3回になる\n30％以下:攻撃回数が4回になる",
      "enemies_that_can_use_skill_count": 0,
      "enemies_that_can_use_skill_sample": [],
      "avails": [
        176606,
        176606,
        176607,
        176608
      ]
    },
    "611292": {
      "skill_id": 611292,
      "use_count": 2,
      "name_id": 102727,
      "name_best": "まわしげり",
      "detail_id": 102743,
      "detail_best": "<skl_target_type>に<skl_exec_count>回の<skl_attribute_name><skl_calc_type>攻撃(威力 <skl_avail_value>)\n雷・風弱点を突ける(ダメージ計算は<skl_attribute_name><skl_calc_type>)\nさらに、雷・風弱点を付与(各2回)\n攻撃対象毎に対象のHPに応じて弱点の付与数が変化\n60％以下:付与数が4回になる\n30％以下:付与数が6回になる<sidenote>\n弱点付与:付与方法によらず弱点毎に回数は合算(最大9回)\n元からその弱点があればその弱点ダメージ倍率をプラス20％",
      "enemies_that_can_use_skill_count": 0,
      "enemies_that_can_use_skill_sample": [],
      "avails": [
        176624,
        176624,
        176624,
        177510,
        177509,
        177508,
        176625,
        176626,
        176627,
        176628,
        176629,
        176630,
        177511,
        10,
        10
      ]
    },
    "51724": {
      "skill_id": 51724,
      "use_count": 1,
      "name_id": 40195,
      "name_best": "威獄の剣",
      "detail_id": 40237,
      "detail_best": "<skl_target_type>に<skl_attribute_name><skl_calc_type>攻撃(威力 <skl_avail_value>)\n攻撃対象が威圧状態の時威力が1.2倍",
      "enemies_that_can_use_skill_count": 0,
      "enemies_that_can_use_skill_sample": [],
      "avails": [
        9276
      ]
    },
    "51729": {
      "skill_id": 51729,
      "use_count": 1,
      "name_id": 40195,
      "name_best": "威獄の剣",
      "detail_id": 40237,
      "detail_best": "<skl_target_type>に<skl_attribute_name><skl_calc_type>攻撃(威力 <skl_avail_value>)\n攻撃対象が威圧状態の時威力が1.2倍",
      "enemies_that_can_use_skill_count": 0,
      "enemies_that_can_use_skill_sample": [],
      "avails": [
        9277
      ]
    },
    "611291": {
      "skill_id": 611291,
      "use_count": 1,
      "name_id": 102726,
      "name_best": "せいけんづき",
      "detail_id": 102742,
      "detail_best": "<skl_target_type>に<skl_attribute_name><skl_calc_type>攻撃(威力 <skl_avail_value>)\n雷・風弱点を突ける(ダメージ計算は<skl_attribute_name><skl_calc_type>)\n攻撃対象に対象のHPに応じた効果を付与し、威力が変化\n60％以下:杖弱点を付与(2回)、威力が1.5倍\n30％以下:威力が2倍\n※威力倍率が高いほうのみ適用される<sidenote>\n弱点付与:付与方法によらず弱点毎に回数は合算(最大9回)\n元からその弱点があればその弱点ダメージ倍率をプラス20％",
      "enemies_that_can_use_skill_count": 0,
      "enemies_that_can_use_skill_sample": [],
      "avails": [
        176622,
        176623
      ]
    },
    "611296": {
      "skill_id": 611296,
      "use_count": 1,
      "name_id": 102731,
      "name_best": "バギマ",
      "detail_id": 102747,
      "detail_best": "<skl_target_type>に2回の<skl_attribute_name><skl_calc_type>攻撃(威力 <skl_avail_value>)\n攻撃対象毎に対象のHPに応じて威力・攻撃回数が変化\n60％以下:攻撃回数が4回になる\n30％以下:威力が1.5倍",
      "enemies_that_can_use_skill_count": 0,
      "enemies_that_can_use_skill_sample": [],
      "avails": [
        176640,
        176640,
        176641,
        176641
      ]
    },
    "611302": {
      "skill_id": 611302,
      "use_count": 1,
      "name_id": 102731,
      "name_best": "バギマ",
      "detail_id": 102747,
      "detail_best": "<skl_target_type>に2回の<skl_attribute_name><skl_calc_type>攻撃(威力 <skl_avail_value>)\n攻撃対象毎に対象のHPに応じて威力・攻撃回数が変化\n60％以下:攻撃回数が4回になる\n30％以下:威力が1.5倍",
      "enemies_that_can_use_skill_count": 0,
      "enemies_that_can_use_skill_sample": [],
      "avails": [
        176640,
        176640,
        176641,
        176641
      ]
    },
    "611299": {
      "skill_id": 611299,
      "use_count": 1,
      "name_id": 102734,
      "name_best": "バギクロス",
      "detail_id": 102750,
      "detail_best": "<skl_target_type>に2回の<skl_attribute_name><skl_calc_type>攻撃(威力 <skl_avail_value>)\n攻撃対象毎に対象のHPに応じて威力・攻撃回数が変化\n60％以下:攻撃回数が4回になる\n30％以下:威力が2倍",
      "enemies_that_can_use_skill_count": 0,
      "enemies_that_can_use_skill_sample": [],
      "avails": [
        176646,
        176646,
        176647,
        176647
      ]
    },
    "611304": {
      "skill_id": 611304,
      "use_count": 1,
      "name_id": 102734,
      "name_best": "バギクロス",
      "detail_id": 102750,
      "detail_best": "<skl_target_type>に2回の<skl_attribute_name><skl_calc_type>攻撃(威力 <skl_avail_value>)\n攻撃対象毎に対象のHPに応じて威力・攻撃回数が変化\n60％以下:攻撃回数が4回になる\n30％以下:威力が2倍",
      "enemies_that_can_use_skill_count": 0,
      "enemies_that_can_use_skill_sample": [],
      "avails": [
        176646,
        176646,
        176647,
        176647
      ]
    },
    "611305": {
      "skill_id": 611305,
      "use_count": 1,
      "name_id": 102734,
      "name_best": "バギクロス",
      "detail_id": 102751,
      "detail_best": "<skl_target_type>に2回の<skl_attribute_name><skl_calc_type>攻撃(威力 <skl_avail_value>)\nさらに、風耐性ダウン<skl_ailment_value>％の効果を付与(<skl_turn_count>)\n攻撃対象毎に対象のHPに応じて威力・攻撃回数が変化\n60％以下:攻撃回数が4回になる\n30％以下:威力が3倍",
      "enemies_that_can_use_skill_count": 0,
      "enemies_that_can_use_skill_sample": [],
      "avails": [
        176648,
        176648,
        176649,
        176649,
        176650
      ]
    },
    "602783": {
      "skill_id": 602783,
      "use_count": 1,
      "name_id": 40255,
      "name_best": "雷剣将の凶撃",
      "detail_id": 40258,
      "detail_best": "<skl_target_type>に<skl_attribute_name><skl_calc_type>攻撃(威力 <skl_avail_value>)<skl_add_damage_limit_text>\n攻撃対象が威圧状態の時威力が1.2倍",
      "enemies_that_can_use_skill_count": 0,
      "enemies_that_can_use_skill_sample": [],
      "avails": [
        64662
      ]
    },
    "611021": {
      "skill_id": 611021,
      "use_count": 1,
      "name_id": 103114,
      "name_best": "活性アーカーコイル",
      "detail_id": 103116,
      "detail_best": "<skl_target_type>のHP回復(回復量 対象の最大HPの<skl_avail_value>％/後衛選択可能)\n回復対象が戦闘不能時は復活させる(回復量 最大HPの<skl_avail_value2>％)\nその後、同対象のSP回復(回復量 対象の最大SPの<skl_avail_value3>％)し、BPを<skl_avail_value4>回復\n※戦闘中3回のみ使用可能",
      "enemies_that_can_use_skill_count": 0,
      "enemies_that_can_use_skill_sample": [],
      "avails": [
        177119,
        177120,
        177121,
        177122
      ]
    },
    "1610021": {
      "skill_id": 1610021,
      "use_count": 1,
      "name_id": 101430,
      "name_best": "献命激両断",
      "detail_id": 101448,
      "detail_best": "自身にHPバリアを付与(効果量 使用者の最大HPの<skl_avail_value>％/重複不可)\nさらに、<skl_target_type3>に<skl_attribute_name>物理攻撃(威力 <skl_avail_value3>)\nこのアビリティのダメージ上限が50000アップ\nHP10％以下になるまで\n自身の最大HPの10％消耗(最大8回)し\n消耗した回数分、威力アップ\n最大2.6倍(8回消耗時)\n※この効果によって自身は戦闘不能にならない",
      "enemies_that_can_use_skill_count": 0,
      "enemies_that_can_use_skill_sample": [],
      "avails": [
        74884,
        74885,
        74886
      ]
    },
    "611565": {
      "skill_id": 611565,
      "use_count": 1,
      "name_id": 103876,
      "name_best": "波及攻渦",
      "detail_id": 103878,
      "detail_best": "<skl_target_type>に「氷属性」攻撃でクリティカル時のダメージ倍率が\n1.6倍になる効果を付与(通常時は1.25倍)\n効果対象がHP満タン時:さらに、それぞれに特殊効果“波及攻渦”を付与<sidenote>\n波及攻渦:属性攻撃でクリティカルが発生する効果",
      "enemies_that_can_use_skill_count": 0,
      "enemies_that_can_use_skill_sample": [],
      "avails": [
        78445,
        78672
      ]
    },
    "1602783": {
      "skill_id": 1602783,
      "use_count": 1,
      "name_id": 40255,
      "name_best": "雷剣将の凶撃",
      "detail_id": 40258,
      "detail_best": "<skl_target_type>に<skl_attribute_name><skl_calc_type>攻撃(威力 <skl_avail_value>)<skl_add_damage_limit_text>\n攻撃対象が威圧状態の時威力が1.2倍",
      "enemies_that_can_use_skill_count": 0,
      "enemies_that_can_use_skill_sample": [],
      "avails": [
        164662
      ]
    },
    "2602783": {
      "skill_id": 2602783,
      "use_count": 1,
      "name_id": 40255,
      "name_best": "雷剣将の凶撃",
      "detail_id": 40258,
      "detail_best": "<skl_target_type>に<skl_attribute_name><skl_calc_type>攻撃(威力 <skl_avail_value>)<skl_add_damage_limit_text>\n攻撃対象が威圧状態の時威力が1.2倍",
      "enemies_that_can_use_skill_count": 0,
      "enemies_that_can_use_skill_sample": [],
      "avails": [
        264662
      ]
    },
    "11602783": {
      "skill_id": 11602783,
      "use_count": 1,
      "name_id": 40255,
      "name_best": "雷剣将の凶撃",
      "detail_id": 40258,
      "detail_best": "<skl_target_type>に<skl_attribute_name><skl_calc_type>攻撃(威力 <skl_avail_value>)<skl_add_damage_limit_text>\n攻撃対象が威圧状態の時威力が1.2倍",
      "enemies_that_can_use_skill_count": 0,
      "enemies_that_can_use_skill_sample": [],
      "avails": [
        1164662
      ]
    },
    "12602783": {
      "skill_id": 12602783,
      "use_count": 1,
      "name_id": 40255,
      "name_best": "雷剣将の凶撃",
      "detail_id": 40258,
      "detail_best": "<skl_target_type>に<skl_attribute_name><skl_calc_type>攻撃(威力 <skl_avail_value>)<skl_add_damage_limit_text>\n攻撃対象が威圧状態の時威力が1.2倍",
      "enemies_that_can_use_skill_count": 0,
      "enemies_that_can_use_skill_sample": [],
      "avails": [
        1264662
      ]
    },
    "21602783": {
      "skill_id": 21602783,
      "use_count": 1,
      "name_id": 40255,
      "name_best": "雷剣将の凶撃",
      "detail_id": 40258,
      "detail_best": "<skl_target_type>に<skl_attribute_name><skl_calc_type>攻撃(威力 <skl_avail_value>)<skl_add_damage_limit_text>\n攻撃対象が威圧状態の時威力が1.2倍",
      "enemies_that_can_use_skill_count": 0,
      "enemies_that_can_use_skill_sample": [],
      "avails": [
        2164662
      ]
    },
    "22602783": {
      "skill_id": 22602783,
      "use_count": 1,
      "name_id": 40255,
      "name_best": "雷剣将の凶撃",
      "detail_id": 40258,
      "detail_best": "<skl_target_type>に<skl_attribute_name><skl_calc_type>攻撃(威力 <skl_avail_value>)<skl_add_damage_limit_text>\n攻撃対象が威圧状態の時威力が1.2倍",
      "enemies_that_can_use_skill_count": 0,
      "enemies_that_can_use_skill_sample": [],
      "avails": [
        2264662
      ]
    },
    "111602783": {
      "skill_id": 111602783,
      "use_count": 1,
      "name_id": 40255,
      "name_best": "雷剣将の凶撃",
      "detail_id": 40258,
      "detail_best": "<skl_target_type>に<skl_attribute_name><skl_calc_type>攻撃(威力 <skl_avail_value>)<skl_add_damage_limit_text>\n攻撃対象が威圧状態の時威力が1.2倍",
      "enemies_that_can_use_skill_count": 0,
      "enemies_that_can_use_skill_sample": [],
      "avails": [
        11164662
      ]
    },
    "112602783": {
      "skill_id": 112602783,
      "use_count": 1,
      "name_id": 40255,
      "name_best": "雷剣将の凶撃",
      "detail_id": 40258,
      "detail_best": "<skl_target_type>に<skl_attribute_name><skl_calc_type>攻撃(威力 <skl_avail_value>)<skl_add_damage_limit_text>\n攻撃対象が威圧状態の時威力が1.2倍",
      "enemies_that_can_use_skill_count": 0,
      "enemies_that_can_use_skill_sample": [],
      "avails": [
        11264662
      ]
    },
    "121602783": {
      "skill_id": 121602783,
      "use_count": 1,
      "name_id": 40255,
      "name_best": "雷剣将の凶撃",
      "detail_id": 40258,
      "detail_best": "<skl_target_type>に<skl_attribute_name><skl_calc_type>攻撃(威力 <skl_avail_value>)<skl_add_damage_limit_text>\n攻撃対象が威圧状態の時威力が1.2倍",
      "enemies_that_can_use_skill_count": 0,
      "enemies_that_can_use_skill_sample": [],
      "avails": [
        12164662
      ]
    },
    "122602783": {
      "skill_id": 122602783,
      "use_count": 1,
      "name_id": 40255,
      "name_best": "雷剣将の凶撃",
      "detail_id": 40258,
      "detail_best": "<skl_target_type>に<skl_attribute_name><skl_calc_type>攻撃(威力 <skl_avail_value>)<skl_add_damage_limit_text>\n攻撃対象が威圧状態の時威力が1.2倍",
      "enemies_that_can_use_skill_count": 0,
      "enemies_that_can_use_skill_sample": [],
      "avails": [
        12264662
      ]
    },
    "211602783": {
      "skill_id": 211602783,
      "use_count": 1,
      "name_id": 40255,
      "name_best": "雷剣将の凶撃",
      "detail_id": 40258,
      "detail_best": "<skl_target_type>に<skl_attribute_name><skl_calc_type>攻撃(威力 <skl_avail_value>)<skl_add_damage_limit_text>\n攻撃対象が威圧状態の時威力が1.2倍",
      "enemies_that_can_use_skill_count": 0,
      "enemies_that_can_use_skill_sample": [],
      "avails": [
        21164662
      ]
    },
    "212602783": {
      "skill_id": 212602783,
      "use_count": 1,
      "name_id": 40255,
      "name_best": "雷剣将の凶撃",
      "detail_id": 40258,
      "detail_best": "<skl_target_type>に<skl_attribute_name><skl_calc_type>攻撃(威力 <skl_avail_value>)<skl_add_damage_limit_text>\n攻撃対象が威圧状態の時威力が1.2倍",
      "enemies_that_can_use_skill_count": 0,
      "enemies_that_can_use_skill_sample": [],
      "avails": [
        21264662
      ]
    },
    "221602783": {
      "skill_id": 221602783,
      "use_count": 1,
      "name_id": 40255,
      "name_best": "雷剣将の凶撃",
      "detail_id": 40258,
      "detail_best": "<skl_target_type>に<skl_attribute_name><skl_calc_type>攻撃(威力 <skl_avail_value>)<skl_add_damage_limit_text>\n攻撃対象が威圧状態の時威力が1.2倍",
      "enemies_that_can_use_skill_count": 0,
      "enemies_that_can_use_skill_sample": [],
      "avails": [
        22164662
      ]
    },
    "222602783": {
      "skill_id": 222602783,
      "use_count": 1,
      "name_id": 40255,
      "name_best": "雷剣将の凶撃",
      "detail_id": 40258,
      "detail_best": "<skl_target_type>に<skl_attribute_name><skl_calc_type>攻撃(威力 <skl_avail_value>)<skl_add_damage_limit_text>\n攻撃対象が威圧状態の時威力が1.2倍",
      "enemies_that_can_use_skill_count": 0,
      "enemies_that_can_use_skill_sample": [],
      "avails": [
        22264662
      ]
    },
    "1111602783": {
      "skill_id": 1111602783,
      "use_count": 1,
      "name_id": 40255,
      "name_best": "雷剣将の凶撃",
      "detail_id": 40258,
      "detail_best": "<skl_target_type>に<skl_attribute_name><skl_calc_type>攻撃(威力 <skl_avail_value>)<skl_add_damage_limit_text>\n攻撃対象が威圧状態の時威力が1.2倍",
      "enemies_that_can_use_skill_count": 0,
      "enemies_that_can_use_skill_sample": [],
      "avails": [
        111164662
      ]
    },
    "1112602783": {
      "skill_id": 1112602783,
      "use_count": 1,
      "name_id": 40255,
      "name_best": "雷剣将の凶撃",
      "detail_id": 40258,
      "detail_best": "<skl_target_type>に<skl_attribute_name><skl_calc_type>攻撃(威力 <skl_avail_value>)<skl_add_damage_limit_text>\n攻撃対象が威圧状態の時威力が1.2倍",
      "enemies_that_can_use_skill_count": 0,
      "enemies_that_can_use_skill_sample": [],
      "avails": [
        111264662
      ]
    },
    "1121602783": {
      "skill_id": 1121602783,
      "use_count": 1,
      "name_id": 40255,
      "name_best": "雷剣将の凶撃",
      "detail_id": 40258,
      "detail_best": "<skl_target_type>に<skl_attribute_name><skl_calc_type>攻撃(威力 <skl_avail_value>)<skl_add_damage_limit_text>\n攻撃対象が威圧状態の時威力が1.2倍",
      "enemies_that_can_use_skill_count": 0,
      "enemies_that_can_use_skill_sample": [],
      "avails": [
        112164662
      ]
    },
    "1122602783": {
      "skill_id": 1122602783,
      "use_count": 1,
      "name_id": 40255,
      "name_best": "雷剣将の凶撃",
      "detail_id": 40258,
      "detail_best": "<skl_target_type>に<skl_attribute_name><skl_calc_type>攻撃(威力 <skl_avail_value>)<skl_add_damage_limit_text>\n攻撃対象が威圧状態の時威力が1.2倍",
      "enemies_that_can_use_skill_count": 0,
      "enemies_that_can_use_skill_sample": [],
      "avails": [
        112264662
      ]
    },
    "1211602783": {
      "skill_id": 1211602783,
      "use_count": 1,
      "name_id": 40255,
      "name_best": "雷剣将の凶撃",
      "detail_id": 40258,
      "detail_best": "<skl_target_type>に<skl_attribute_name><skl_calc_type>攻撃(威力 <skl_avail_value>)<skl_add_damage_limit_text>\n攻撃対象が威圧状態の時威力が1.2倍",
      "enemies_that_can_use_skill_count": 0,
      "enemies_that_can_use_skill_sample": [],
      "avails": [
        121164662
      ]
    }
  },
  "enemy_groups": {},
  "uses_sample": [
    {
      "condition_id": 17,
      "param": 50,
      "slot": 0,
      "subsystem": "SkillConditionList",
      "owner_table": "SkillConditionList",
      "owner_row_id": 167,
      "ailment_type": 0,
      "status_type": 0,
      "weapon_type": 0,
      "magic_type": 0,
      "equipment": 0,
      "tactical_list_id": 0,
      "tactical_action_id": 0,
      "enemy_id": 0,
      "enemy_label": "",
      "enemy_name_best": "",
      "enemy_group_id": 0,
      "enemy_group_label": "",
      "enemy_group_enemies": null,
      "skill_id": 52089,
      "skill_index": -1,
      "skill_avail_id": 9984,
      "skill_condition_list_id": 167,
      "condition_ref_field": "m_InvokeCondition|AND",
      "select_type": -1,
      "turn_count": -1,
      "group_index": -1,
      "friendly_index": -999,
      "priority_skill": -999,
      "co_conditions_in_row": []
    },
    {
      "condition_id": 17,
      "param": 20,
      "slot": 0,
      "subsystem": "SkillConditionList",
      "owner_table": "SkillConditionList",
      "owner_row_id": 168,
      "ailment_type": 0,
      "status_type": 0,
      "weapon_type": 0,
      "magic_type": 0,
      "equipment": 0,
      "tactical_list_id": 0,
      "tactical_action_id": 0,
      "enemy_id": 0,
      "enemy_label": "",
      "enemy_name_best": "",
      "enemy_group_id": 0,
      "enemy_group_label": "",
      "enemy_group_enemies": null,
      "skill_id": 52089,
      "skill_index": -1,
      "skill_avail_id": 9985,
      "skill_condition_list_id": 168,
      "condition_ref_field": "m_InvokeCondition|AND",
      "select_type": -1,
      "turn_count": -1,
      "group_index": -1,
      "friendly_index": -999,
      "priority_skill": -999,
      "co_conditions_in_row": []
    },
    {
      "condition_id": 17,
      "param": 100,
      "slot": 0,
      "subsystem": "SkillConditionList",
      "owner_table": "SkillConditionList",
      "owner_row_id": 172,
      "ailment_type": 0,
      "status_type": 0,
      "weapon_type": 0,
      "magic_type": 0,
      "equipment": 0,
      "tactical_list_id": 0,
      "tactical_action_id": 0,
      "enemy_id": 0,
      "enemy_label": "",
      "enemy_name_best": "",
      "enemy_group_id": 0,
      "enemy_group_label": "",
      "enemy_group_enemies": null,
      "skill_id": 52089,
      "skill_index": -1,
      "skill_avail_id": 9975,
      "skill_condition_list_id": 172,
      "condition_ref_field": "m_InvokeCondition|AND",
      "select_type": -1,
      "turn_count": -1,
      "group_index": -1,
      "friendly_index": -999,
      "priority_skill": -999,
      "co_conditions_in_row": []
    },
    {
      "condition_id": 17,
      "param": 30,
      "slot": 0,
      "subsystem": "SkillConditionList",
      "owner_table": "SkillConditionList",
      "owner_row_id": 21,
      "ailment_type": 0,
      "status_type": 0,
      "weapon_type": 0,
      "magic_type": 0,
      "equipment": 0,
      "tactical_list_id": 0,
      "tactical_action_id": 0,
      "enemy_id": 0,
      "enemy_label": "",
      "enemy_name_best": "",
      "enemy_group_id": 0,
      "enemy_group_label": "",
      "enemy_group_enemies": null,
      "skill_id": 51724,
      "skill_index": -1,
      "skill_avail_id": 9276,
      "skill_condition_list_id": 21,
      "condition_ref_field": "m_SkillAvailMagnificationCondition|AND",
      "select_type": -1,
      "turn_count": -1,
      "group_index": -1,
      "friendly_index": -999,
      "priority_skill": -999,
      "co_conditions_in_row": []
    },
    {
      "condition_id": 17,
      "param": 30,
      "slot": 0,
      "subsystem": "SkillConditionList",
      "owner_table": "SkillConditionList",
      "owner_row_id": 21,
      "ailment_type": 0,
      "status_type": 0,
      "weapon_type": 0,
      "magic_type": 0,
      "equipment": 0,
      "tactical_list_id": 0,
      "tactical_action_id": 0,
      "enemy_id": 0,
      "enemy_label": "",
      "enemy_name_best": "",
      "enemy_group_id": 0,
      "enemy_group_label": "",
      "enemy_group_enemies": null,
      "skill_id": 51729,
      "skill_index": -1,
      "skill_avail_id": 9277,
      "skill_condition_list_id": 21,
      "condition_ref_field": "m_SkillAvailMagnificationCondition|AND",
      "select_type": -1,
      "turn_count": -1,
      "group_index": -1,
      "friendly_index": -999,
      "priority_skill": -999,
      "co_conditions_in_row": []
    },
    {
      "condition_id": 17,
      "param": 60,
      "slot": 0,
      "subsystem": "SkillConditionList",
      "owner_table": "SkillConditionList",
      "owner_row_id": 638,
      "ailment_type": 0,
      "status_type": 0,
      "weapon_type": 0,
      "magic_type": 0,
      "equipment": 0,
      "tactical_list_id": 0,
      "tactical_action_id": 0,
      "enemy_id": 0,
      "enemy_label": "",
      "enemy_name_best": "",
      "enemy_group_id": 0,
      "enemy_group_label": "",
      "enemy_group_enemies": null,
      "skill_id": 611286,
      "skill_index": -1,
      "skill_avail_id": 176607,
      "skill_condition_list_id": 638,
      "condition_ref_field": "m_InvokeCondition|AND",
      "select_type": -1,
      "turn_count": -1,
      "group_index": -1,
      "friendly_index": -999,
      "priority_skill": -999,
      "co_conditions_in_row": []
    },
    {
      "condition_id": 17,
      "param": 30,
      "slot": 0,
      "subsystem": "SkillConditionList",
      "owner_table": "SkillConditionList",
      "owner_row_id": 21,
      "ailment_type": 0,
      "status_type": 0,
      "weapon_type": 0,
      "magic_type": 0,
      "equipment": 0,
      "tactical_list_id": 0,
      "tactical_action_id": 0,
      "enemy_id": 0,
      "enemy_label": "",
      "enemy_name_best": "",
      "enemy_group_id": 0,
      "enemy_group_label": "",
      "enemy_group_enemies": null,
      "skill_id": 611286,
      "skill_index": -1,
      "skill_avail_id": 176608,
      "skill_condition_list_id": 21,
      "condition_ref_field": "m_InvokeCondition|AND",
      "select_type": -1,
      "turn_count": -1,
      "group_index": -1,
      "friendly_index": -999,
      "priority_skill": -999,
      "co_conditions_in_row": []
    },
    {
      "condition_id": 17,
      "param": 60,
      "slot": 0,
      "subsystem": "SkillConditionList",
      "owner_table": "SkillConditionList",
      "owner_row_id": 638,
      "ailment_type": 0,
      "status_type": 0,
      "weapon_type": 0,
      "magic_type": 0,
      "equipment": 0,
      "tactical_list_id": 0,
      "tactical_action_id": 0,
      "enemy_id": 0,
      "enemy_label": "",
      "enemy_name_best": "",
      "enemy_group_id": 0,
      "enemy_group_label": "",
      "enemy_group_enemies": null,
      "skill_id": 611288,
      "skill_index": -1,
      "skill_avail_id": 176614,
      "skill_condition_list_id": 638,
      "condition_ref_field": "m_InvokeCondition|AND",
      "select_type": -1,
      "turn_count": -1,
      "group_index": -1,
      "friendly_index": -999,
      "priority_skill": -999,
      "co_conditions_in_row": []
    },
    {
      "condition_id": 17,
      "param": 60,
      "slot": 0,
      "subsystem": "SkillConditionList",
      "owner_table": "SkillConditionList",
      "owner_row_id": 638,
      "ailment_type": 0,
      "status_type": 0,
      "weapon_type": 0,
      "magic_type": 0,
      "equipment": 0,
      "tactical_list_id": 0,
      "tactical_action_id": 0,
      "enemy_id": 0,
      "enemy_label": "",
      "enemy_name_best": "",
      "enemy_group_id": 0,
      "enemy_group_label": "",
      "enemy_group_enemies": null,
      "skill_id": 611288,
      "skill_index": -1,
      "skill_avail_id": 176615,
      "skill_condition_list_id": 638,
      "condition_ref_field": "m_InvokeCondition|AND",
      "select_type": -1,
      "turn_count": -1,
      "group_index": -1,
      "friendly_index": -999,
      "priority_skill": -999,
      "co_conditions_in_row": []
    },
    {
      "condition_id": 17,
      "param": 30,
      "slot": 0,
      "subsystem": "SkillConditionList",
      "owner_table": "SkillConditionList",
      "owner_row_id": 21,
      "ailment_type": 0,
      "status_type": 0,
      "weapon_type": 0,
      "magic_type": 0,
      "equipment": 0,
      "tactical_list_id": 0,
      "tactical_action_id": 0,
      "enemy_id": 0,
      "enemy_label": "",
      "enemy_name_best": "",
      "enemy_group_id": 0,
      "enemy_group_label": "",
      "enemy_group_enemies": null,
      "skill_id": 611288,
      "skill_index": -1,
      "skill_avail_id": 176616,
      "skill_condition_list_id": 21,
      "condition_ref_field": "m_InvokeCondition|AND",
      "select_type": -1,
      "turn_count": -1,
      "group_index": -1,
      "friendly_index": -999,
      "priority_skill": -999,
      "co_conditions_in_row": []
    },
    {
      "condition_id": 17,
      "param": 30,
      "slot": 0,
      "subsystem": "SkillConditionList",
      "owner_table": "SkillConditionList",
      "owner_row_id": 21,
      "ailment_type": 0,
      "status_type": 0,
      "weapon_type": 0,
      "magic_type": 0,
      "equipment": 0,
      "tactical_list_id": 0,
      "tactical_action_id": 0,
      "enemy_id": 0,
      "enemy_label": "",
      "enemy_name_best": "",
      "enemy_group_id": 0,
      "enemy_group_label": "",
      "enemy_group_enemies": null,
      "skill_id": 611288,
      "skill_index": -1,
      "skill_avail_id": 176617,
      "skill_condition_list_id": 21,
      "condition_ref_field": "m_InvokeCondition|AND",
      "select_type": -1,
      "turn_count": -1,
      "group_index": -1,
      "friendly_index": -999,
      "priority_skill": -999,
      "co_conditions_in_row": []
    },
    {
      "condition_id": 17,
      "param": 60,
      "slot": 0,
      "subsystem": "SkillConditionList",
      "owner_table": "SkillConditionList",
      "owner_row_id": 638,
      "ailment_type": 0,
      "status_type": 0,
      "weapon_type": 0,
      "magic_type": 0,
      "equipment": 0,
      "tactical_list_id": 0,
      "tactical_action_id": 0,
      "enemy_id": 0,
      "enemy_label": "",
      "enemy_name_best": "",
      "enemy_group_id": 0,
      "enemy_group_label": "",
      "enemy_group_enemies": null,
      "skill_id": 611291,
      "skill_index": -1,
      "skill_avail_id": 176623,
      "skill_condition_list_id": 638,
      "condition_ref_field": "m_InvokeCondition|AND",
      "select_type": -1,
      "turn_count": -1,
      "group_index": -1,
      "friendly_index": -999,
      "priority_skill": -999,
      "co_conditions_in_row": []
    },
    {
      "condition_id": 17,
      "param": 60,
      "slot": 1,
      "subsystem": "SkillConditionList",
      "owner_table": "SkillConditionList",
      "owner_row_id": 718,
      "ailment_type": 0,
      "status_type": 0,
      "weapon_type": 0,
      "magic_type": 0,
      "equipment": 0,
      "tactical_list_id": 0,
      "tactical_action_id": 0,
      "enemy_id": 0,
      "enemy_label": "",
      "enemy_name_best": "",
      "enemy_group_id": 0,
      "enemy_group_label": "",
      "enemy_group_enemies": null,
      "skill_id": 611292,
      "skill_index": -1,
      "skill_avail_id": 177509,
      "skill_condition_list_id": 718,
      "condition_ref_field": "m_InvokeCondition|AND",
      "select_type": -1,
      "turn_count": -1,
      "group_index": -1,
      "friendly_index": -999,
      "priority_skill": -999,
      "co_conditions_in_row": [
        18,
        10724
      ]
    },
    {
      "condition_id": 17,
      "param": 30,
      "slot": 0,
      "subsystem": "SkillConditionList",
      "owner_table": "SkillConditionList",
      "owner_row_id": 719,
      "ailment_type": 0,
      "status_type": 0,
      "weapon_type": 0,
      "magic_type": 0,
      "equipment": 0,
      "tactical_list_id": 0,
      "tactical_action_id": 0,
      "enemy_id": 0,
      "enemy_label": "",
      "enemy_name_best": "",
      "enemy_group_id": 0,
      "enemy_group_label": "",
      "enemy_group_enemies": null,
      "skill_id": 611292,
      "skill_index": -1,
      "skill_avail_id": 177510,
      "skill_condition_list_id": 719,
      "condition_ref_field": "m_InvokeCondition|AND",
      "select_type": -1,
      "turn_count": -1,
      "group_index": -1,
      "friendly_index": -999,
      "priority_skill": -999,
      "co_conditions_in_row": []
    },
    {
      "condition_id": 17,
      "param": 60,
      "slot": 0,
      "subsystem": "SkillConditionList",
      "owner_table": "SkillConditionList",
      "owner_row_id": 638,
      "ailment_type": 0,
      "status_type": 0,
      "weapon_type": 0,
      "magic_type": 0,
      "equipment": 0,
      "tactical_list_id": 0,
      "tactical_action_id": 0,
      "enemy_id": 0,
      "enemy_label": "",
      "enemy_name_best": "",
      "enemy_group_id": 0,
      "enemy_group_label": "",
      "enemy_group_enemies": null,
      "skill_id": 611296,
      "skill_index": -1,
      "skill_avail_id": 176641,
      "skill_condition_list_id": 638,
      "condition_ref_field": "m_InvokeCondition|AND",
      "select_type": -1,
      "turn_count": -1,
      "group_index": -1,
      "friendly_index": -999,
      "priority_skill": -999,
      "co_conditions_in_row": []
    },
    {
      "condition_id": 17,
      "param": 60,
      "slot": 0,
      "subsystem": "SkillConditionList",
      "owner_table": "SkillConditionList",
      "owner_row_id": 638,
      "ailment_type": 0,
      "status_type": 0,
      "weapon_type": 0,
      "magic_type": 0,
      "equipment": 0,
      "tactical_list_id": 0,
      "tactical_action_id": 0,
      "enemy_id": 0,
      "enemy_label": "",
      "enemy_name_best": "",
      "enemy_group_id": 0,
      "enemy_group_label": "",
      "enemy_group_enemies": null,
      "skill_id": 611302,
      "skill_index": -1,
      "skill_avail_id": 176641,
      "skill_condition_list_id": 638,
      "condition_ref_field": "m_InvokeCondition|AND",
      "select_type": -1,
      "turn_count": -1,
      "group_index": -1,
      "friendly_index": -999,
      "priority_skill": -999,
      "co_conditions_in_row": []
    },
    {
      "condition_id": 17,
      "param": 60,
      "slot": 0,
      "subsystem": "SkillConditionList",
      "owner_table": "SkillConditionList",
      "owner_row_id": 638,
      "ailment_type": 0,
      "status_type": 0,
      "weapon_type": 0,
      "magic_type": 0,
      "equipment": 0,
      "tactical_list_id": 0,
      "tactical_action_id": 0,
      "enemy_id": 0,
      "enemy_label": "",
      "enemy_name_best": "",
      "enemy_group_id": 0,
      "enemy_group_label": "",
      "enemy_group_enemies": null,
      "skill_id": 611299,
      "skill_index": -1,
      "skill_avail_id": 176647,
      "skill_condition_list_id": 638,
      "condition_ref_field": "m_InvokeCondition|AND",
      "select_type": -1,
      "turn_count": -1,
      "group_index": -1,
      "friendly_index": -999,
      "priority_skill": -999,
      "co_conditions_in_row": []
    },
    {
      "condition_id": 17,
      "param": 60,
      "slot": 0,
      "subsystem": "SkillConditionList",
      "owner_table": "SkillConditionList",
      "owner_row_id": 638,
      "ailment_type": 0,
      "status_type": 0,
      "weapon_type": 0,
      "magic_type": 0,
      "equipment": 0,
      "tactical_list_id": 0,
      "tactical_action_id": 0,
      "enemy_id": 0,
      "enemy_label": "",
      "enemy_name_best": "",
      "enemy_group_id": 0,
      "enemy_group_label": "",
      "enemy_group_enemies": null,
      "skill_id": 611304,
      "skill_index": -1,
      "skill_avail_id": 176647,
      "skill_condition_list_id": 638,
      "condition_ref_field": "m_InvokeCondition|AND",
      "select_type": -1,
      "turn_count": -1,
      "group_index": -1,
      "friendly_index": -999,
      "priority_skill": -999,
      "co_conditions_in_row": []
    },
    {
      "condition_id": 17,
      "param": 60,
      "slot": 0,
      "subsystem": "SkillConditionList",
      "owner_table": "SkillConditionList",
      "owner_row_id": 638,
      "ailment_type": 0,
      "status_type": 0,
      "weapon_type": 0,
      "magic_type": 0,
      "equipment": 0,
      "tactical_list_id": 0,
      "tactical_action_id": 0,
      "enemy_id": 0,
      "enemy_label": "",
      "enemy_name_best": "",
      "enemy_group_id": 0,
      "enemy_group_label": "",
      "enemy_group_enemies": null,
      "skill_id": 611305,
      "skill_index": -1,
      "skill_avail_id": 176649,
      "skill_condition_list_id": 638,
      "condition_ref_field": "m_InvokeCondition|AND",
      "select_type": -1,
      "turn_count": -1,
      "group_index": -1,
      "friendly_index": -999,
      "priority_skill": -999,
      "co_conditions_in_row": []
    },
    {
      "condition_id": 17,
      "param": 30,
      "slot": 0,
      "subsystem": "SkillConditionList",
      "owner_table": "SkillConditionList",
      "owner_row_id": 21,
      "ailment_type": 0,
      "status_type": 0,
      "weapon_type": 0,
      "magic_type": 0,
      "equipment": 0,
      "tactical_list_id": 0,
      "tactical_action_id": 0,
      "enemy_id": 0,
      "enemy_label": "",
      "enemy_name_best": "",
      "enemy_group_id": 0,
      "enemy_group_label": "",
      "enemy_group_enemies": null,
      "skill_id": 602783,
      "skill_index": -1,
      "skill_avail_id": 64662,
      "skill_condition_list_id": 21,
      "condition_ref_field": "m_SkillAvailMagnificationCondition|AND",
      "select_type": -1,
      "turn_count": -1,
      "group_index": -1,
      "friendly_index": -999,
      "priority_skill": -999,
      "co_conditions_in_row": []
    },
    {
      "condition_id": 17,
      "param": 0,
      "slot": 0,
      "subsystem": "SkillConditionList",
      "owner_table": "SkillConditionList",
      "owner_row_id": 696,
      "ailment_type": 0,
      "status_type": 0,
      "weapon_type": 0,
      "magic_type": 0,
      "equipment": 0,
      "tactical_list_id": 0,
      "tactical_action_id": 0,
      "enemy_id": 0,
      "enemy_label": "",
      "enemy_name_best": "",
      "enemy_group_id": 0,
      "enemy_group_label": "",
      "enemy_group_enemies": null,
      "skill_id": 611021,
      "skill_index": -1,
      "skill_avail_id": 177120,
      "skill_condition_list_id": 696,
      "condition_ref_field": "m_InvokeCondition|AND",
      "select_type": -1,
      "turn_count": -1,
      "group_index": -1,
      "friendly_index": -999,
      "priority_skill": -999,
      "co_conditions_in_row": []
    },
    {
      "condition_id": 17,
      "param": 100,
      "slot": 0,
      "subsystem": "SkillConditionList",
      "owner_table": "SkillConditionList",
      "owner_row_id": 172,
      "ailment_type": 0,
      "status_type": 0,
      "weapon_type": 0,
      "magic_type": 0,
      "equipment": 0,
      "tactical_list_id": 0,
      "tactical_action_id": 0,
      "enemy_id": 0,
      "enemy_label": "",
      "enemy_name_best": "",
      "enemy_group_id": 0,
      "enemy_group_label": "",
      "enemy_group_enemies": null,
      "skill_id": 1610021,
      "skill_index": -1,
      "skill_avail_id": 74886,
      "skill_condition_list_id": 172,
      "condition_ref_field": "m_SkillAvailMagnificationConditionArray|AND",
      "select_type": -1,
      "turn_count": -1,
      "group_index": -1,
      "friendly_index": -999,
      "priority_skill": -999,
      "co_conditions_in_row": []
    },
    {
      "condition_id": 17,
      "param": 100,
      "slot": 0,
      "subsystem": "SkillConditionList",
      "owner_table": "SkillConditionList",
      "owner_row_id": 172,
      "ailment_type": 0,
      "status_type": 0,
      "weapon_type": 0,
      "magic_type": 0,
      "equipment": 0,
      "tactical_list_id": 0,
      "tactical_action_id": 0,
      "enemy_id": 0,
      "enemy_label": "",
      "enemy_name_best": "",
      "enemy_group_id": 0,
      "enemy_group_label": "",
      "enemy_group_enemies": null,
      "skill_id": 611565,
      "skill_index": -1,
      "skill_avail_id": 78445,
      "skill_condition_list_id": 172,
      "condition_ref_field": "m_InvokeCondition|AND",
      "select_type": -1,
      "turn_count": -1,
      "group_index": -1,
      "friendly_index": -999,
      "priority_skill": -999,
      "co_conditions_in_row": []
    },
    {
      "condition_id": 17,
      "param": 81,
      "slot": 0,
      "subsystem": "SkillConditionList",
      "owner_table": "SkillConditionList",
      "owner_row_id": 934,
      "ailment_type": 0,
      "status_type": 0,
      "weapon_type": 0,
      "magic_type": 0,
      "equipment": 0,
      "tactical_list_id": 0,
      "tactical_action_id": 0,
      "enemy_id": 0,
      "enemy_label": "",
      "enemy_name_best": "",
      "enemy_group_id": 0,
      "enemy_group_label": "",
      "enemy_group_enemies": null,
      "skill_id": 612638,
      "skill_index": -1,
      "skill_avail_id": 79338,
      "skill_condition_list_id": 934,
      "condition_ref_field": "m_InvokeCondition|AND",
      "select_type": -1,
      "turn_count": -1,
      "group_index": -1,
      "friendly_index": -999,
      "priority_skill": -999,
      "co_conditions_in_row": []
    },
    {
      "condition_id": 17,
      "param": 81,
      "slot": 0,
      "subsystem": "SkillConditionList",
      "owner_table": "SkillConditionList",
      "owner_row_id": 934,
      "ailment_type": 0,
      "status_type": 0,
      "weapon_type": 0,
      "magic_type": 0,
      "equipment": 0,
      "tactical_list_id": 0,
      "tactical_action_id": 0,
      "enemy_id": 0,
      "enemy_label": "",
      "enemy_name_best": "",
      "enemy_group_id": 0,
      "enemy_group_label": "",
      "enemy_group_enemies": null,
      "skill_id": 612638,
      "skill_index": -1,
      "skill_avail_id": 79339,
      "skill_condition_list_id": 934,
      "condition_ref_field": "m_InvokeCondition|AND",
      "select_type": -1,
      "turn_count": -1,
      "group_index": -1,
      "friendly_index": -999,
      "priority_skill": -999,
      "co_conditions_in_row": []
    },
    {
      "condition_id": 17,
      "param": 81,
      "slot": 0,
      "subsystem": "SkillConditionList",
      "owner_table": "SkillConditionList",
      "owner_row_id": 934,
      "ailment_type": 0,
      "status_type": 0,
      "weapon_type": 0,
      "magic_type": 0,
      "equipment": 0,
      "tactical_list_id": 0,
      "tactical_action_id": 0,
      "enemy_id": 0,
      "enemy_label": "",
      "enemy_name_best": "",
      "enemy_group_id": 0,
      "enemy_group_label": "",
      "enemy_group_enemies": null,
      "skill_id": 612638,
      "skill_index": -1,
      "skill_avail_id": 79340,
      "skill_condition_list_id": 934,
      "condition_ref_field": "m_InvokeCondition|AND",
      "select_type": -1,
      "turn_count": -1,
      "group_index": -1,
      "friendly_index": -999,
      "priority_skill": -999,
      "co_conditions_in_row": []
    },
    {
      "condition_id": 17,
      "param": 30,
      "slot": 0,
      "subsystem": "SkillConditionList",
      "owner_table": "SkillConditionList",
      "owner_row_id": 21,
      "ailment_type": 0,
      "status_type": 0,
      "weapon_type": 0,
      "magic_type": 0,
      "equipment": 0,
      "tactical_list_id": 0,
      "tactical_action_id": 0,
      "enemy_id": 0,
      "enemy_label": "",
      "enemy_name_best": "",
      "enemy_group_id": 0,
      "enemy_group_label": "",
      "enemy_group_enemies": null,
      "skill_id": 1602783,
      "skill_index": -1,
      "skill_avail_id": 164662,
      "skill_condition_list_id": 21,
      "condition_ref_field": "m_SkillAvailMagnificationCondition|AND",
      "select_type": -1,
      "turn_count": -1,
      "group_index": -1,
      "friendly_index": -999,
      "priority_skill": -999,
      "co_conditions_in_row": []
    },
    {
      "condition_id": 17,
      "param": 30,
      "slot": 0,
      "subsystem": "SkillConditionList",
      "owner_table": "SkillConditionList",
      "owner_row_id": 21,
      "ailment_type": 0,
      "status_type": 0,
      "weapon_type": 0,
      "magic_type": 0,
      "equipment": 0,
      "tactical_list_id": 0,
      "tactical_action_id": 0,
      "enemy_id": 0,
      "enemy_label": "",
      "enemy_name_best": "",
      "enemy_group_id": 0,
      "enemy_group_label": "",
      "enemy_group_enemies": null,
      "skill_id": 2602783,
      "skill_index": -1,
      "skill_avail_id": 264662,
      "skill_condition_list_id": 21,
      "condition_ref_field": "m_SkillAvailMagnificationCondition|AND",
      "select_type": -1,
      "turn_count": -1,
      "group_index": -1,
      "friendly_index": -999,
      "priority_skill": -999,
      "co_conditions_in_row": []
    },
    {
      "condition_id": 17,
      "param": 30,
      "slot": 0,
      "subsystem": "SkillConditionList",
      "owner_table": "SkillConditionList",
      "owner_row_id": 21,
      "ailment_type": 0,
      "status_type": 0,
      "weapon_type": 0,
      "magic_type": 0,
      "equipment": 0,
      "tactical_list_id": 0,
      "tactical_action_id": 0,
      "enemy_id": 0,
      "enemy_label": "",
      "enemy_name_best": "",
      "enemy_group_id": 0,
      "enemy_group_label": "",
      "enemy_group_enemies": null,
      "skill_id": 11602783,
      "skill_index": -1,
      "skill_avail_id": 1164662,
      "skill_condition_list_id": 21,
      "condition_ref_field": "m_SkillAvailMagnificationCondition|AND",
      "select_type": -1,
      "turn_count": -1,
      "group_index": -1,
      "friendly_index": -999,
      "priority_skill": -999,
      "co_conditions_in_row": []
    },
    {
      "condition_id": 17,
      "param": 30,
      "slot": 0,
      "subsystem": "SkillConditionList",
      "owner_table": "SkillConditionList",
      "owner_row_id": 21,
      "ailment_type": 0,
      "status_type": 0,
      "weapon_type": 0,
      "magic_type": 0,
      "equipment": 0,
      "tactical_list_id": 0,
      "tactical_action_id": 0,
      "enemy_id": 0,
      "enemy_label": "",
      "enemy_name_best": "",
      "enemy_group_id": 0,
      "enemy_group_label": "",
      "enemy_group_enemies": null,
      "skill_id": 12602783,
      "skill_index": -1,
      "skill_avail_id": 1264662,
      "skill_condition_list_id": 21,
      "condition_ref_field": "m_SkillAvailMagnificationCondition|AND",
      "select_type": -1,
      "turn_count": -1,
      "group_index": -1,
      "friendly_index": -999,
      "priority_skill": -999,
      "co_conditions_in_row": []
    },
    {
      "condition_id": 17,
      "param": 30,
      "slot": 0,
      "subsystem": "SkillConditionList",
      "owner_table": "SkillConditionList",
      "owner_row_id": 21,
      "ailment_type": 0,
      "status_type": 0,
      "weapon_type": 0,
      "magic_type": 0,
      "equipment": 0,
      "tactical_list_id": 0,
      "tactical_action_id": 0,
      "enemy_id": 0,
      "enemy_label": "",
      "enemy_name_best": "",
      "enemy_group_id": 0,
      "enemy_group_label": "",
      "enemy_group_enemies": null,
      "skill_id": 21602783,
      "skill_index": -1,
      "skill_avail_id": 2164662,
      "skill_condition_list_id": 21,
      "condition_ref_field": "m_SkillAvailMagnificationCondition|AND",
      "select_type": -1,
      "turn_count": -1,
      "group_index": -1,
      "friendly_index": -999,
      "priority_skill": -999,
      "co_conditions_in_row": []
    },
    {
      "condition_id": 17,
      "param": 30,
      "slot": 0,
      "subsystem": "SkillConditionList",
      "owner_table": "SkillConditionList",
      "owner_row_id": 21,
      "ailment_type": 0,
      "status_type": 0,
      "weapon_type": 0,
      "magic_type": 0,
      "equipment": 0,
      "tactical_list_id": 0,
      "tactical_action_id": 0,
      "enemy_id": 0,
      "enemy_label": "",
      "enemy_name_best": "",
      "enemy_group_id": 0,
      "enemy_group_label": "",
      "enemy_group_enemies": null,
      "skill_id": 22602783,
      "skill_index": -1,
      "skill_avail_id": 2264662,
      "skill_condition_list_id": 21,
      "condition_ref_field": "m_SkillAvailMagnificationCondition|AND",
      "select_type": -1,
      "turn_count": -1,
      "group_index": -1,
      "friendly_index": -999,
      "priority_skill": -999,
      "co_conditions_in_row": []
    },
    {
      "condition_id": 17,
      "param": 30,
      "slot": 0,
      "subsystem": "SkillConditionList",
      "owner_table": "SkillConditionList",
      "owner_row_id": 21,
      "ailment_type": 0,
      "status_type": 0,
      "weapon_type": 0,
      "magic_type": 0,
      "equipment": 0,
      "tactical_list_id": 0,
      "tactical_action_id": 0,
      "enemy_id": 0,
      "enemy_label": "",
      "enemy_name_best": "",
      "enemy_group_id": 0,
      "enemy_group_label": "",
      "enemy_group_enemies": null,
      "skill_id": 111602783,
      "skill_index": -1,
      "skill_avail_id": 11164662,
      "skill_condition_list_id": 21,
      "condition_ref_field": "m_SkillAvailMagnificationCondition|AND",
      "select_type": -1,
      "turn_count": -1,
      "group_index": -1,
      "friendly_index": -999,
      "priority_skill": -999,
      "co_conditions_in_row": []
    },
    {
      "condition_id": 17,
      "param": 30,
      "slot": 0,
      "subsystem": "SkillConditionList",
      "owner_table": "SkillConditionList",
      "owner_row_id": 21,
      "ailment_type": 0,
      "status_type": 0,
      "weapon_type": 0,
      "magic_type": 0,
      "equipment": 0,
      "tactical_list_id": 0,
      "tactical_action_id": 0,
      "enemy_id": 0,
      "enemy_label": "",
      "enemy_name_best": "",
      "enemy_group_id": 0,
      "enemy_group_label": "",
      "enemy_group_enemies": null,
      "skill_id": 112602783,
      "skill_index": -1,
      "skill_avail_id": 11264662,
      "skill_condition_list_id": 21,
      "condition_ref_field": "m_SkillAvailMagnificationCondition|AND",
      "select_type": -1,
      "turn_count": -1,
      "group_index": -1,
      "friendly_index": -999,
      "priority_skill": -999,
      "co_conditions_in_row": []
    },
    {
      "condition_id": 17,
      "param": 30,
      "slot": 0,
      "subsystem": "SkillConditionList",
      "owner_table": "SkillConditionList",
      "owner_row_id": 21,
      "ailment_type": 0,
      "status_type": 0,
      "weapon_type": 0,
      "magic_type": 0,
      "equipment": 0,
      "tactical_list_id": 0,
      "tactical_action_id": 0,
      "enemy_id": 0,
      "enemy_label": "",
      "enemy_name_best": "",
      "enemy_group_id": 0,
      "enemy_group_label": "",
      "enemy_group_enemies": null,
      "skill_id": 121602783,
      "skill_index": -1,
      "skill_avail_id": 12164662,
      "skill_condition_list_id": 21,
      "condition_ref_field": "m_SkillAvailMagnificationCondition|AND",
      "select_type": -1,
      "turn_count": -1,
      "group_index": -1,
      "friendly_index": -999,
      "priority_skill": -999,
      "co_conditions_in_row": []
    },
    {
      "condition_id": 17,
      "param": 30,
      "slot": 0,
      "subsystem": "SkillConditionList",
      "owner_table": "SkillConditionList",
      "owner_row_id": 21,
      "ailment_type": 0,
      "status_type": 0,
      "weapon_type": 0,
      "magic_type": 0,
      "equipment": 0,
      "tactical_list_id": 0,
      "tactical_action_id": 0,
      "enemy_id": 0,
      "enemy_label": "",
      "enemy_name_best": "",
      "enemy_group_id": 0,
      "enemy_group_label": "",
      "enemy_group_enemies": null,
      "skill_id": 122602783,
      "skill_index": -1,
      "skill_avail_id": 12264662,
      "skill_condition_list_id": 21,
      "condition_ref_field": "m_SkillAvailMagnificationCondition|AND",
      "select_type": -1,
      "turn_count": -1,
      "group_index": -1,
      "friendly_index": -999,
      "priority_skill": -999,
      "co_conditions_in_row": []
    },
    {
      "condition_id": 17,
      "param": 30,
      "slot": 0,
      "subsystem": "SkillConditionList",
      "owner_table": "SkillConditionList",
      "owner_row_id": 21,
      "ailment_type": 0,
      "status_type": 0,
      "weapon_type": 0,
      "magic_type": 0,
      "equipment": 0,
      "tactical_list_id": 0,
      "tactical_action_id": 0,
      "enemy_id": 0,
      "enemy_label": "",
      "enemy_name_best": "",
      "enemy_group_id": 0,
      "enemy_group_label": "",
      "enemy_group_enemies": null,
      "skill_id": 211602783,
      "skill_index": -1,
      "skill_avail_id": 21164662,
      "skill_condition_list_id": 21,
      "condition_ref_field": "m_SkillAvailMagnificationCondition|AND",
      "select_type": -1,
      "turn_count": -1,
      "group_index": -1,
      "friendly_index": -999,
      "priority_skill": -999,
      "co_conditions_in_row": []
    },
    {
      "condition_id": 17,
      "param": 30,
      "slot": 0,
      "subsystem": "SkillConditionList",
      "owner_table": "SkillConditionList",
      "owner_row_id": 21,
      "ailment_type": 0,
      "status_type": 0,
      "weapon_type": 0,
      "magic_type": 0,
      "equipment": 0,
      "tactical_list_id": 0,
      "tactical_action_id": 0,
      "enemy_id": 0,
      "enemy_label": "",
      "enemy_name_best": "",
      "enemy_group_id": 0,
      "enemy_group_label": "",
      "enemy_group_enemies": null,
      "skill_id": 212602783,
      "skill_index": -1,
      "skill_avail_id": 21264662,
      "skill_condition_list_id": 21,
      "condition_ref_field": "m_SkillAvailMagnificationCondition|AND",
      "select_type": -1,
      "turn_count": -1,
      "group_index": -1,
      "friendly_index": -999,
      "priority_skill": -999,
      "co_conditions_in_row": []
    },
    {
      "condition_id": 17,
      "param": 30,
      "slot": 0,
      "subsystem": "SkillConditionList",
      "owner_table": "SkillConditionList",
      "owner_row_id": 21,
      "ailment_type": 0,
      "status_type": 0,
      "weapon_type": 0,
      "magic_type": 0,
      "equipment": 0,
      "tactical_list_id": 0,
      "tactical_action_id": 0,
      "enemy_id": 0,
      "enemy_label": "",
      "enemy_name_best": "",
      "enemy_group_id": 0,
      "enemy_group_label": "",
      "enemy_group_enemies": null,
      "skill_id": 221602783,
      "skill_index": -1,
      "skill_avail_id": 22164662,
      "skill_condition_list_id": 21,
      "condition_ref_field": "m_SkillAvailMagnificationCondition|AND",
      "select_type": -1,
      "turn_count": -1,
      "group_index": -1,
      "friendly_index": -999,
      "priority_skill": -999,
      "co_conditions_in_row": []
    },
    {
      "condition_id": 17,
      "param": 30,
      "slot": 0,
      "subsystem": "SkillConditionList",
      "owner_table": "SkillConditionList",
      "owner_row_id": 21,
      "ailment_type": 0,
      "status_type": 0,
      "weapon_type": 0,
      "magic_type": 0,
      "equipment": 0,
      "tactical_list_id": 0,
      "tactical_action_id": 0,
      "enemy_id": 0,
      "enemy_label": "",
      "enemy_name_best": "",
      "enemy_group_id": 0,
      "enemy_group_label": "",
      "enemy_group_enemies": null,
      "skill_id": 222602783,
      "skill_index": -1,
      "skill_avail_id": 22264662,
      "skill_condition_list_id": 21,
      "condition_ref_field": "m_SkillAvailMagnificationCondition|AND",
      "select_type": -1,
      "turn_count": -1,
      "group_index": -1,
      "friendly_index": -999,
      "priority_skill": -999,
      "co_conditions_in_row": []
    },
    {
      "condition_id": 17,
      "param": 30,
      "slot": 0,
      "subsystem": "SkillConditionList",
      "owner_table": "SkillConditionList",
      "owner_row_id": 21,
      "ailment_type": 0,
      "status_type": 0,
      "weapon_type": 0,
      "magic_type": 0,
      "equipment": 0,
      "tactical_list_id": 0,
      "tactical_action_id": 0,
      "enemy_id": 0,
      "enemy_label": "",
      "enemy_name_best": "",
      "enemy_group_id": 0,
      "enemy_group_label": "",
      "enemy_group_enemies": null,
      "skill_id": 1111602783,
      "skill_index": -1,
      "skill_avail_id": 111164662,
      "skill_condition_list_id": 21,
      "condition_ref_field": "m_SkillAvailMagnificationCondition|AND",
      "select_type": -1,
      "turn_count": -1,
      "group_index": -1,
      "friendly_index": -999,
      "priority_skill": -999,
      "co_conditions_in_row": []
    },
    {
      "condition_id": 17,
      "param": 30,
      "slot": 0,
      "subsystem": "SkillConditionList",
      "owner_table": "SkillConditionList",
      "owner_row_id": 21,
      "ailment_type": 0,
      "status_type": 0,
      "weapon_type": 0,
      "magic_type": 0,
      "equipment": 0,
      "tactical_list_id": 0,
      "tactical_action_id": 0,
      "enemy_id": 0,
      "enemy_label": "",
      "enemy_name_best": "",
      "enemy_group_id": 0,
      "enemy_group_label": "",
      "enemy_group_enemies": null,
      "skill_id": 1112602783,
      "skill_index": -1,
      "skill_avail_id": 111264662,
      "skill_condition_list_id": 21,
      "condition_ref_field": "m_SkillAvailMagnificationCondition|AND",
      "select_type": -1,
      "turn_count": -1,
      "group_index": -1,
      "friendly_index": -999,
      "priority_skill": -999,
      "co_conditions_in_row": []
    },
    {
      "condition_id": 17,
      "param": 30,
      "slot": 0,
      "subsystem": "SkillConditionList",
      "owner_table": "SkillConditionList",
      "owner_row_id": 21,
      "ailment_type": 0,
      "status_type": 0,
      "weapon_type": 0,
      "magic_type": 0,
      "equipment": 0,
      "tactical_list_id": 0,
      "tactical_action_id": 0,
      "enemy_id": 0,
      "enemy_label": "",
      "enemy_name_best": "",
      "enemy_group_id": 0,
      "enemy_group_label": "",
      "enemy_group_enemies": null,
      "skill_id": 1121602783,
      "skill_index": -1,
      "skill_avail_id": 112164662,
      "skill_condition_list_id": 21,
      "condition_ref_field": "m_SkillAvailMagnificationCondition|AND",
      "select_type": -1,
      "turn_count": -1,
      "group_index": -1,
      "friendly_index": -999,
      "priority_skill": -999,
      "co_conditions_in_row": []
    },
    {
      "condition_id": 17,
      "param": 30,
      "slot": 0,
      "subsystem": "SkillConditionList",
      "owner_table": "SkillConditionList",
      "owner_row_id": 21,
      "ailment_type": 0,
      "status_type": 0,
      "weapon_type": 0,
      "magic_type": 0,
      "equipment": 0,
      "tactical_list_id": 0,
      "tactical_action_id": 0,
      "enemy_id": 0,
      "enemy_label": "",
      "enemy_name_best": "",
      "enemy_group_id": 0,
      "enemy_group_label": "",
      "enemy_group_enemies": null,
      "skill_id": 1122602783,
      "skill_index": -1,
      "skill_avail_id": 112264662,
      "skill_condition_list_id": 21,
      "condition_ref_field": "m_SkillAvailMagnificationCondition|AND",
      "select_type": -1,
      "turn_count": -1,
      "group_index": -1,
      "friendly_index": -999,
      "priority_skill": -999,
      "co_conditions_in_row": []
    },
    {
      "condition_id": 17,
      "param": 30,
      "slot": 0,
      "subsystem": "SkillConditionList",
      "owner_table": "SkillConditionList",
      "owner_row_id": 21,
      "ailment_type": 0,
      "status_type": 0,
      "weapon_type": 0,
      "magic_type": 0,
      "equipment": 0,
      "tactical_list_id": 0,
      "tactical_action_id": 0,
      "enemy_id": 0,
      "enemy_label": "",
      "enemy_name_best": "",
      "enemy_group_id": 0,
      "enemy_group_label": "",
      "enemy_group_enemies": null,
      "skill_id": 1211602783,
      "skill_index": -1,
      "skill_avail_id": 121164662,
      "skill_condition_list_id": 21,
      "condition_ref_field": "m_SkillAvailMagnificationCondition|AND",
      "select_type": -1,
      "turn_count": -1,
      "group_index": -1,
      "friendly_index": -999,
      "priority_skill": -999,
      "co_conditions_in_row": []
    }
  ]
}