{
  "condition_id": 716,
  "total_uses": 30,
  "uses_by_subsystem": {
    "TacticalList": 29,
    "BattleEventList": 1
  },
  "uses_by_table": {
    "TacticalList": 29,
    "BattleEventList": 1
  },
  "uses_by_subsystem_slot": {
    "TacticalList[0]": 24,
    "TacticalList[1]": 5,
    "BattleEventList[0]": 1
  },
  "param_stats": {
    "count": 30,
    "min": 0,
    "max": 0,
    "mean": 0.0,
    "median": 0.0,
    "p10": 0,
    "p25": 0,
    "p75": 0,
    "p90": 0,
    "top10": [
      [
        0,
        30
      ]
    ]
  },
  "filter_histograms": {
    "ailment_type": [],
    "status_type": [],
    "weapon_type": [],
    "magic_type": [],
    "equipment": []
  },
  "cooccurrence_top": [
    [
      10301,
      15
    ],
    [
      10712,
      14
    ],
    [
      648,
      5
    ],
    [
      10713,
      5
    ],
    [
      701,
      2
    ],
    [
      10715,
      2
    ]
  ],
  "top_enemies": [
    {
      "enemy_id": 15127,
      "use_count": 5,
      "label": "AGM_Boss_Chp4_02_01__B5127",
      "name_best": "Sonzon the Flameguard",
      "type_id": 121781,
      "tactical_assign_id": 30252,
      "skills_id": 51363
    },
    {
      "enemy_id": 32655,
      "use_count": 5,
      "label": "Rematch_Season20_Boss02_01",
      "name_best": "Sonzon the Flameguard",
      "type_id": 121781,
      "tactical_assign_id": 30252,
      "skills_id": 51993
    },
    {
      "enemy_id": 33150,
      "use_count": 5,
      "label": "Enemy_JobTowerThi_f0005_r002EX_002",
      "name_best": "Trial Great Thief's Henchman",
      "type_id": 22971,
      "tactical_assign_id": 130602,
      "skills_id": 52193
    },
    {
      "enemy_id": 5060,
      "use_count": 1,
      "label": "AllMASTER_Boss_Chp8_ESFP",
      "name_best": "Edoras Defender of Fame",
      "type_id": 10070,
      "tactical_assign_id": 10106,
      "skills_id": 10072
    },
    {
      "enemy_id": 5068,
      "use_count": 1,
      "label": "AllMASTER_Boss_Chp8_ESFP_2",
      "name_best": "Edoras Defender of Fame",
      "type_id": 10070,
      "tactical_assign_id": 10106,
      "skills_id": 10072
    },
    {
      "enemy_id": 15060,
      "use_count": 1,
      "label": "AllMASTER_Boss_Chp8_ESFP__B5060",
      "name_best": "Edoras Defender of Fame",
      "type_id": 110070,
      "tactical_assign_id": 110106,
      "skills_id": 10072
    },
    {
      "enemy_id": 15068,
      "use_count": 1,
      "label": "AllMASTER_Boss_Chp8_ESFP_2__B5068",
      "name_best": "Edoras Defender of Fame",
      "type_id": 110070,
      "tactical_assign_id": 110106,
      "skills_id": 10072
    },
    {
      "enemy_id": 32279,
      "use_count": 1,
      "label": "Rematch_Season06_Boss01_03",
      "name_best": "Edoras Defender of Fame",
      "type_id": 110070,
      "tactical_assign_id": 110106,
      "skills_id": 10072
    },
    {
      "enemy_id": 99415,
      "use_count": 1,
      "label": "AllMASTER_Boss_Chp8_ESFP_1_easy",
      "name_best": "Edoras Defender of Fame",
      "type_id": 110070,
      "tactical_assign_id": 110106,
      "skills_id": 10072
    },
    {
      "enemy_id": 99418,
      "use_count": 1,
      "label": "AllMASTER_Boss_Chp8_ESFP_2_1_easy",
      "name_best": "Edoras Defender of Fame",
      "type_id": 110070,
      "tactical_assign_id": 110106,
      "skills_id": 10072
    },
    {
      "enemy_id": 99433,
      "use_count": 1,
      "label": "Rematch_Season06_Boss01_03_1_easy",
      "name_best": "Edoras Defender of Fame",
      "type_id": 110070,
      "tactical_assign_id": 110106,
      "skills_id": 10072
    },
    {
      "enemy_id": 99421,
      "use_count": 1,
      "label": "AllMASTER_Boss_Chp8_ESFP_1",
      "name_best": "Edoras Defender of Fame",
      "type_id": 110070,
      "tactical_assign_id": 110106,
      "skills_id": 10072
    },
    {
      "enemy_id": 99424,
      "use_count": 1,
      "label": "AllMASTER_Boss_Chp8_ESFP_2_1",
      "name_best": "Edoras Defender of Fame",
      "type_id": 110070,
      "tactical_assign_id": 110106,
      "skills_id": 10072
    },
    {
      "enemy_id": 99436,
      "use_count": 1,
      "label": "Rematch_Season06_Boss01_03_1",
      "name_best": "Edoras Defender of Fame",
      "type_id": 110070,
      "tactical_assign_id": 110106,
      "skills_id": 10072
    },
    {
      "enemy_id": 99427,
      "use_count": 1,
      "label": "AllMASTER_Boss_Chp8_ESFP_1_hard",
      "name_best": "Edoras Defender of Fame",
      "type_id": 110070,
      "tactical_assign_id": 110106,
      "skills_id": 10072
    },
    {
      "enemy_id": 99430,
      "use_count": 1,
      "label": "AllMASTER_Boss_Chp8_ESFP_2_1_hard",
      "name_best": "Edoras Defender of Fame",
      "type_id": 110070,
      "tactical_assign_id": 110106,
      "skills_id": 10072
    },
    {
      "enemy_id": 99439,
      "use_count": 1,
      "label": "Rematch_Season06_Boss01_03_1_hard",
      "name_best": "Edoras Defender of Fame",
      "type_id": 110070,
      "tactical_assign_id": 110106,
      "skills_id": 10072
    }
  ],
  "top_skills": {},
  "enemy_groups": {
    "19308": {
      "enemy_group_id": 19308,
      "use_count": 1,
      "label": "AllMaster_Boss_ENG08__B9308",
      "formation": 59,
      "bgm": 107,
      "event_indices": [
        1,
        5
      ],
      "enemy_ids": [
        15047
      ],
      "enemy_labels": [
        "AllMASTER_Boss_Chp5_03_01__B5047"
      ],
      "enemy_names_best": [
        "King Pardis III"
      ]
    }
  },
  "uses_sample": [
    {
      "condition_id": 716,
      "param": 0,
      "slot": 0,
      "subsystem": "TacticalList",
      "owner_table": "TacticalList",
      "owner_row_id": 7042,
      "ailment_type": 0,
      "status_type": 0,
      "weapon_type": 0,
      "magic_type": 0,
      "equipment": 0,
      "tactical_list_id": 7042,
      "tactical_action_id": 0,
      "enemy_id": 5060,
      "enemy_label": "AllMASTER_Boss_Chp8_ESFP",
      "enemy_name_best": "Edoras Defender of Fame",
      "enemy_group_id": 0,
      "enemy_group_label": "",
      "enemy_group_enemies": null,
      "skill_id": 0,
      "skill_index": -1,
      "skill_avail_id": 0,
      "skill_condition_list_id": 0,
      "condition_ref_field": "",
      "select_type": -1,
      "turn_count": -1,
      "group_index": -1,
      "friendly_index": -999,
      "priority_skill": -999,
      "co_conditions_in_row": []
    },
    {
      "condition_id": 716,
      "param": 0,
      "slot": 0,
      "subsystem": "TacticalList",
      "owner_table": "TacticalList",
      "owner_row_id": 7042,
      "ailment_type": 0,
      "status_type": 0,
      "weapon_type": 0,
      "magic_type": 0,
      "equipment": 0,
      "tactical_list_id": 7042,
      "tactical_action_id": 0,
      "enemy_id": 5068,
      "enemy_label": "AllMASTER_Boss_Chp8_ESFP_2",
      "enemy_name_best": "Edoras Defender of Fame",
      "enemy_group_id": 0,
      "enemy_group_label": "",
      "enemy_group_enemies": null,
      "skill_id": 0,
      "skill_index": -1,
      "skill_avail_id": 0,
      "skill_condition_list_id": 0,
      "condition_ref_field": "",
      "select_type": -1,
      "turn_count": -1,
      "group_index": -1,
      "friendly_index": -999,
      "priority_skill": -999,
      "co_conditions_in_row": []
    },
    {
      "condition_id": 716,
      "param": 0,
      "slot": 0,
      "subsystem": "TacticalList",
      "owner_table": "TacticalList",
      "owner_row_id": 7042,
      "ailment_type": 0,
      "status_type": 0,
      "weapon_type": 0,
      "magic_type": 0,
      "equipment": 0,
      "tactical_list_id": 7042,
      "tactical_action_id": 0,
      "enemy_id": 15060,
      "enemy_label": "AllMASTER_Boss_Chp8_ESFP__B5060",
      "enemy_name_best": "Edoras Defender of Fame",
      "enemy_group_id": 0,
      "enemy_group_label": "",
      "enemy_group_enemies": null,
      "skill_id": 0,
      "skill_index": -1,
      "skill_avail_id": 0,
      "skill_condition_list_id": 0,
      "condition_ref_field": "",
      "select_type": -1,
      "turn_count": -1,
      "group_index": -1,
      "friendly_index": -999,
      "priority_skill": -999,
      "co_conditions_in_row": []
    },
    {
      "condition_id": 716,
      "param": 0,
      "slot": 0,
      "subsystem": "TacticalList",
      "owner_table": "TacticalList",
      "owner_row_id": 7042,
      "ailment_type": 0,
      "status_type": 0,
      "weapon_type": 0,
      "magic_type": 0,
      "equipment": 0,
      "tactical_list_id": 7042,
      "tactical_action_id": 0,
      "enemy_id": 15068,
      "enemy_label": "AllMASTER_Boss_Chp8_ESFP_2__B5068",
      "enemy_name_best": "Edoras Defender of Fame",
      "enemy_group_id": 0,
      "enemy_group_label": "",
      "enemy_group_enemies": null,
      "skill_id": 0,
      "skill_index": -1,
      "skill_avail_id": 0,
      "skill_condition_list_id": 0,
      "condition_ref_field": "",
      "select_type": -1,
      "turn_count": -1,
      "group_index": -1,
      "friendly_index": -999,
      "priority_skill": -999,
      "co_conditions_in_row": []
    },
    {
      "condition_id": 716,
      "param": 0,
      "slot": 0,
      "subsystem": "TacticalList",
      "owner_table": "TacticalList",
      "owner_row_id": 7042,
      "ailment_type": 0,
      "status_type": 0,
      "weapon_type": 0,
      "magic_type": 0,
      "equipment": 0,
      "tactical_list_id": 7042,
      "tactical_action_id": 0,
      "enemy_id": 32279,
      "enemy_label": "Rematch_Season06_Boss01_03",
      "enemy_name_best": "Edoras Defender of Fame",
      "enemy_group_id": 0,
      "enemy_group_label": "",
      "enemy_group_enemies": null,
      "skill_id": 0,
      "skill_index": -1,
      "skill_avail_id": 0,
      "skill_condition_list_id": 0,
      "condition_ref_field": "",
      "select_type": -1,
      "turn_count": -1,
      "group_index": -1,
      "friendly_index": -999,
      "priority_skill": -999,
      "co_conditions_in_row": []
    },
    {
      "condition_id": 716,
      "param": 0,
      "slot": 0,
      "subsystem": "TacticalList",
      "owner_table": "TacticalList",
      "owner_row_id": 7042,
      "ailment_type": 0,
      "status_type": 0,
      "weapon_type": 0,
      "magic_type": 0,
      "equipment": 0,
      "tactical_list_id": 7042,
      "tactical_action_id": 0,
      "enemy_id": 99415,
      "enemy_label": "AllMASTER_Boss_Chp8_ESFP_1_easy",
      "enemy_name_best": "Edoras Defender of Fame",
      "enemy_group_id": 0,
      "enemy_group_label": "",
      "enemy_group_enemies": null,
      "skill_id": 0,
      "skill_index": -1,
      "skill_avail_id": 0,
      "skill_condition_list_id": 0,
      "condition_ref_field": "",
      "select_type": -1,
      "turn_count": -1,
      "group_index": -1,
      "friendly_index": -999,
      "priority_skill": -999,
      "co_conditions_in_row": []
    },
    {
      "condition_id": 716,
      "param": 0,
      "slot": 0,
      "subsystem": "TacticalList",
      "owner_table": "TacticalList",
      "owner_row_id": 7042,
      "ailment_type": 0,
      "status_type": 0,
      "weapon_type": 0,
      "magic_type": 0,
      "equipment": 0,
      "tactical_list_id": 7042,
      "tactical_action_id": 0,
      "enemy_id": 99418,
      "enemy_label": "AllMASTER_Boss_Chp8_ESFP_2_1_easy",
      "enemy_name_best": "Edoras Defender of Fame",
      "enemy_group_id": 0,
      "enemy_group_label": "",
      "enemy_group_enemies": null,
      "skill_id": 0,
      "skill_index": -1,
      "skill_avail_id": 0,
      "skill_condition_list_id": 0,
      "condition_ref_field": "",
      "select_type": -1,
      "turn_count": -1,
      "group_index": -1,
      "friendly_index": -999,
      "priority_skill": -999,
      "co_conditions_in_row": []
    },
    {
      "condition_id": 716,
      "param": 0,
      "slot": 0,
      "subsystem": "TacticalList",
      "owner_table": "TacticalList",
      "owner_row_id": 7042,
      "ailment_type": 0,
      "status_type": 0,
      "weapon_type": 0,
      "magic_type": 0,
      "equipment": 0,
      "tactical_list_id": 7042,
      "tactical_action_id": 0,
      "enemy_id": 99433,
      "enemy_label": "Rematch_Season06_Boss01_03_1_easy",
      "enemy_name_best": "Edoras Defender of Fame",
      "enemy_group_id": 0,
      "enemy_group_label": "",
      "enemy_group_enemies": null,
      "skill_id": 0,
      "skill_index": -1,
      "skill_avail_id": 0,
      "skill_condition_list_id": 0,
      "condition_ref_field": "",
      "select_type": -1,
      "turn_count": -1,
      "group_index": -1,
      "friendly_index": -999,
      "priority_skill": -999,
      "co_conditions_in_row": []
    },
    {
      "condition_id": 716,
      "param": 0,
      "slot": 0,
      "subsystem": "TacticalList",
      "owner_table": "TacticalList",
      "owner_row_id": 7042,
      "ailment_type": 0,
      "status_type": 0,
      "weapon_type": 0,
      "magic_type": 0,
      "equipment": 0,
      "tactical_list_id": 7042,
      "tactical_action_id": 0,
      "enemy_id": 99421,
      "enemy_label": "AllMASTER_Boss_Chp8_ESFP_1",
      "enemy_name_best": "Edoras Defender of Fame",
      "enemy_group_id": 0,
      "enemy_group_label": "",
      "enemy_group_enemies": null,
      "skill_id": 0,
      "skill_index": -1,
      "skill_avail_id": 0,
      "skill_condition_list_id": 0,
      "condition_ref_field": "",
      "select_type": -1,
      "turn_count": -1,
      "group_index": -1,
      "friendly_index": -999,
      "priority_skill": -999,
      "co_conditions_in_row": []
    },
    {
      "condition_id": 716,
      "param": 0,
      "slot": 0,
      "subsystem": "TacticalList",
      "owner_table": "TacticalList",
      "owner_row_id": 7042,
      "ailment_type": 0,
      "status_type": 0,
      "weapon_type": 0,
      "magic_type": 0,
      "equipment": 0,
      "tactical_list_id": 7042,
      "tactical_action_id": 0,
      "enemy_id": 99424,
      "enemy_label": "AllMASTER_Boss_Chp8_ESFP_2_1",
      "enemy_name_best": "Edoras Defender of Fame",
      "enemy_group_id": 0,
      "enemy_group_label": "",
      "enemy_group_enemies": null,
      "skill_id": 0,
      "skill_index": -1,
      "skill_avail_id": 0,
      "skill_condition_list_id": 0,
      "condition_ref_field": "",
      "select_type": -1,
      "turn_count": -1,
      "group_index": -1,
      "friendly_index": -999,
      "priority_skill": -999,
      "co_conditions_in_row": []
    },
    {
      "condition_id": 716,
      "param": 0,
      "slot": 0,
      "subsystem": "TacticalList",
      "owner_table": "TacticalList",
      "owner_row_id": 7042,
      "ailment_type": 0,
      "status_type": 0,
      "weapon_type": 0,
      "magic_type": 0,
      "equipment": 0,
      "tactical_list_id": 7042,
      "tactical_action_id": 0,
      "enemy_id": 99436,
      "enemy_label": "Rematch_Season06_Boss01_03_1",
      "enemy_name_best": "Edoras Defender of Fame",
      "enemy_group_id": 0,
      "enemy_group_label": "",
      "enemy_group_enemies": null,
      "skill_id": 0,
      "skill_index": -1,
      "skill_avail_id": 0,
      "skill_condition_list_id": 0,
      "condition_ref_field": "",
      "select_type": -1,
      "turn_count": -1,
      "group_index": -1,
      "friendly_index": -999,
      "priority_skill": -999,
      "co_conditions_in_row": []
    },
    {
      "condition_id": 716,
      "param": 0,
      "slot": 0,
      "subsystem": "TacticalList",
      "owner_table": "TacticalList",
      "owner_row_id": 7042,
      "ailment_type": 0,
      "status_type": 0,
      "weapon_type": 0,
      "magic_type": 0,
      "equipment": 0,
      "tactical_list_id": 7042,
      "tactical_action_id": 0,
      "enemy_id": 99427,
      "enemy_label": "AllMASTER_Boss_Chp8_ESFP_1_hard",
      "enemy_name_best": "Edoras Defender of Fame",
      "enemy_group_id": 0,
      "enemy_group_label": "",
      "enemy_group_enemies": null,
      "skill_id": 0,
      "skill_index": -1,
      "skill_avail_id": 0,
      "skill_condition_list_id": 0,
      "condition_ref_field": "",
      "select_type": -1,
      "turn_count": -1,
      "group_index": -1,
      "friendly_index": -999,
      "priority_skill": -999,
      "co_conditions_in_row": []
    },
    {
      "condition_id": 716,
      "param": 0,
      "slot": 0,
      "subsystem": "TacticalList",
      "owner_table": "TacticalList",
      "owner_row_id": 7042,
      "ailment_type": 0,
      "status_type": 0,
      "weapon_type": 0,
      "magic_type": 0,
      "equipment": 0,
      "tactical_list_id": 7042,
      "tactical_action_id": 0,
      "enemy_id": 99430,
      "enemy_label": "AllMASTER_Boss_Chp8_ESFP_2_1_hard",
      "enemy_name_best": "Edoras Defender of Fame",
      "enemy_group_id": 0,
      "enemy_group_label": "",
      "enemy_group_enemies": null,
      "skill_id": 0,
      "skill_index": -1,
      "skill_avail_id": 0,
      "skill_condition_list_id": 0,
      "condition_ref_field": "",
      "select_type": -1,
      "turn_count": -1,
      "group_index": -1,
      "friendly_index": -999,
      "priority_skill": -999,
      "co_conditions_in_row": []
    },
    {
      "condition_id": 716,
      "param": 0,
      "slot": 0,
      "subsystem": "TacticalList",
      "owner_table": "TacticalList",
      "owner_row_id": 7042,
      "ailment_type": 0,
      "status_type": 0,
      "weapon_type": 0,
      "magic_type": 0,
      "equipment": 0,
      "tactical_list_id": 7042,
      "tactical_action_id": 0,
      "enemy_id": 99439,
      "enemy_label": "Rematch_Season06_Boss01_03_1_hard",
      "enemy_name_best": "Edoras Defender of Fame",
      "enemy_group_id": 0,
      "enemy_group_label": "",
      "enemy_group_enemies": null,
      "skill_id": 0,
      "skill_index": -1,
      "skill_avail_id": 0,
      "skill_condition_list_id": 0,
      "condition_ref_field": "",
      "select_type": -1,
      "turn_count": -1,
      "group_index": -1,
      "friendly_index": -999,
      "priority_skill": -999,
      "co_conditions_in_row": []
    },
    {
      "condition_id": 716,
      "param": 0,
      "slot": 0,
      "subsystem": "TacticalList",
      "owner_table": "TacticalList",
      "owner_row_id": 21735,
      "ailment_type": 0,
      "status_type": 0,
      "weapon_type": 0,
      "magic_type": 0,
      "equipment": 0,
      "tactical_list_id": 21735,
      "tactical_action_id": 0,
      "enemy_id": 15127,
      "enemy_label": "AGM_Boss_Chp4_02_01__B5127",
      "enemy_name_best": "Sonzon the Flameguard",
      "enemy_group_id": 0,
      "enemy_group_label": "",
      "enemy_group_enemies": null,
      "skill_id": 0,
      "skill_index": -1,
      "skill_avail_id": 0,
      "skill_condition_list_id": 0,
      "condition_ref_field": "",
      "select_type": -1,
      "turn_count": -1,
      "group_index": -1,
      "friendly_index": -999,
      "priority_skill": -999,
      "co_conditions_in_row": [
        10301,
        10712
      ]
    },
    {
      "condition_id": 716,
      "param": 0,
      "slot": 0,
      "subsystem": "TacticalList",
      "owner_table": "TacticalList",
      "owner_row_id": 21735,
      "ailment_type": 0,
      "status_type": 0,
      "weapon_type": 0,
      "magic_type": 0,
      "equipment": 0,
      "tactical_list_id": 21735,
      "tactical_action_id": 0,
      "enemy_id": 32655,
      "enemy_label": "Rematch_Season20_Boss02_01",
      "enemy_name_best": "Sonzon the Flameguard",
      "enemy_group_id": 0,
      "enemy_group_label": "",
      "enemy_group_enemies": null,
      "skill_id": 0,
      "skill_index": -1,
      "skill_avail_id": 0,
      "skill_condition_list_id": 0,
      "condition_ref_field": "",
      "select_type": -1,
      "turn_count": -1,
      "group_index": -1,
      "friendly_index": -999,
      "priority_skill": -999,
      "co_conditions_in_row": [
        10301,
        10712
      ]
    },
    {
      "condition_id": 716,
      "param": 0,
      "slot": 0,
      "subsystem": "TacticalList",
      "owner_table": "TacticalList",
      "owner_row_id": 21693,
      "ailment_type": 0,
      "status_type": 0,
      "weapon_type": 0,
      "magic_type": 0,
      "equipment": 0,
      "tactical_list_id": 21693,
      "tactical_action_id": 0,
      "enemy_id": 15127,
      "enemy_label": "AGM_Boss_Chp4_02_01__B5127",
      "enemy_name_best": "Sonzon the Flameguard",
      "enemy_group_id": 0,
      "enemy_group_label": "",
      "enemy_group_enemies": null,
      "skill_id": 0,
      "skill_index": -1,
      "skill_avail_id": 0,
      "skill_condition_list_id": 0,
      "condition_ref_field": "",
      "select_type": -1,
      "turn_count": -1,
      "group_index": -1,
      "friendly_index": -999,
      "priority_skill": -999,
      "co_conditions_in_row": [
        10301,
        10712
      ]
    },
    {
      "condition_id": 716,
      "param": 0,
      "slot": 0,
      "subsystem": "TacticalList",
      "owner_table": "TacticalList",
      "owner_row_id": 21693,
      "ailment_type": 0,
      "status_type": 0,
      "weapon_type": 0,
      "magic_type": 0,
      "equipment": 0,
      "tactical_list_id": 21693,
      "tactical_action_id": 0,
      "enemy_id": 32655,
      "enemy_label": "Rematch_Season20_Boss02_01",
      "enemy_name_best": "Sonzon the Flameguard",
      "enemy_group_id": 0,
      "enemy_group_label": "",
      "enemy_group_enemies": null,
      "skill_id": 0,
      "skill_index": -1,
      "skill_avail_id": 0,
      "skill_condition_list_id": 0,
      "condition_ref_field": "",
      "select_type": -1,
      "turn_count": -1,
      "group_index": -1,
      "friendly_index": -999,
      "priority_skill": -999,
      "co_conditions_in_row": [
        10301,
        10712
      ]
    },
    {
      "condition_id": 716,
      "param": 0,
      "slot": 0,
      "subsystem": "TacticalList",
      "owner_table": "TacticalList",
      "owner_row_id": 21739,
      "ailment_type": 0,
      "status_type": 0,
      "weapon_type": 0,
      "magic_type": 0,
      "equipment": 0,
      "tactical_list_id": 21739,
      "tactical_action_id": 0,
      "enemy_id": 15127,
      "enemy_label": "AGM_Boss_Chp4_02_01__B5127",
      "enemy_name_best": "Sonzon the Flameguard",
      "enemy_group_id": 0,
      "enemy_group_label": "",
      "enemy_group_enemies": null,
      "skill_id": 0,
      "skill_index": -1,
      "skill_avail_id": 0,
      "skill_condition_list_id": 0,
      "condition_ref_field": "",
      "select_type": -1,
      "turn_count": -1,
      "group_index": -1,
      "friendly_index": -999,
      "priority_skill": -999,
      "co_conditions_in_row": [
        701,
        10301,
        10712
      ]
    },
    {
      "condition_id": 716,
      "param": 0,
      "slot": 0,
      "subsystem": "TacticalList",
      "owner_table": "TacticalList",
      "owner_row_id": 21739,
      "ailment_type": 0,
      "status_type": 0,
      "weapon_type": 0,
      "magic_type": 0,
      "equipment": 0,
      "tactical_list_id": 21739,
      "tactical_action_id": 0,
      "enemy_id": 32655,
      "enemy_label": "Rematch_Season20_Boss02_01",
      "enemy_name_best": "Sonzon the Flameguard",
      "enemy_group_id": 0,
      "enemy_group_label": "",
      "enemy_group_enemies": null,
      "skill_id": 0,
      "skill_index": -1,
      "skill_avail_id": 0,
      "skill_condition_list_id": 0,
      "condition_ref_field": "",
      "select_type": -1,
      "turn_count": -1,
      "group_index": -1,
      "friendly_index": -999,
      "priority_skill": -999,
      "co_conditions_in_row": [
        701,
        10301,
        10712
      ]
    },
    {
      "condition_id": 716,
      "param": 0,
      "slot": 0,
      "subsystem": "TacticalList",
      "owner_table": "TacticalList",
      "owner_row_id": 21734,
      "ailment_type": 0,
      "status_type": 0,
      "weapon_type": 0,
      "magic_type": 0,
      "equipment": 0,
      "tactical_list_id": 21734,
      "tactical_action_id": 0,
      "enemy_id": 15127,
      "enemy_label": "AGM_Boss_Chp4_02_01__B5127",
      "enemy_name_best": "Sonzon the Flameguard",
      "enemy_group_id": 0,
      "enemy_group_label": "",
      "enemy_group_enemies": null,
      "skill_id": 0,
      "skill_index": -1,
      "skill_avail_id": 0,
      "skill_condition_list_id": 0,
      "condition_ref_field": "",
      "select_type": -1,
      "turn_count": -1,
      "group_index": -1,
      "friendly_index": -999,
      "priority_skill": -999,
      "co_conditions_in_row": [
        10301,
        10712,
        10715
      ]
    },
    {
      "condition_id": 716,
      "param": 0,
      "slot": 0,
      "subsystem": "TacticalList",
      "owner_table": "TacticalList",
      "owner_row_id": 21734,
      "ailment_type": 0,
      "status_type": 0,
      "weapon_type": 0,
      "magic_type": 0,
      "equipment": 0,
      "tactical_list_id": 21734,
      "tactical_action_id": 0,
      "enemy_id": 32655,
      "enemy_label": "Rematch_Season20_Boss02_01",
      "enemy_name_best": "Sonzon the Flameguard",
      "enemy_group_id": 0,
      "enemy_group_label": "",
      "enemy_group_enemies": null,
      "skill_id": 0,
      "skill_index": -1,
      "skill_avail_id": 0,
      "skill_condition_list_id": 0,
      "condition_ref_field": "",
      "select_type": -1,
      "turn_count": -1,
      "group_index": -1,
      "friendly_index": -999,
      "priority_skill": -999,
      "co_conditions_in_row": [
        10301,
        10712,
        10715
      ]
    },
    {
      "condition_id": 716,
      "param": 0,
      "slot": 0,
      "subsystem": "TacticalList",
      "owner_table": "TacticalList",
      "owner_row_id": 21729,
      "ailment_type": 0,
      "status_type": 0,
      "weapon_type": 0,
      "magic_type": 0,
      "equipment": 0,
      "tactical_list_id": 21729,
      "tactical_action_id": 0,
      "enemy_id": 15127,
      "enemy_label": "AGM_Boss_Chp4_02_01__B5127",
      "enemy_name_best": "Sonzon the Flameguard",
      "enemy_group_id": 0,
      "enemy_group_label": "",
      "enemy_group_enemies": null,
      "skill_id": 0,
      "skill_index": -1,
      "skill_avail_id": 0,
      "skill_condition_list_id": 0,
      "condition_ref_field": "",
      "select_type": -1,
      "turn_count": -1,
      "group_index": -1,
      "friendly_index": -999,
      "priority_skill": -999,
      "co_conditions_in_row": [
        10301,
        10712
      ]
    },
    {
      "condition_id": 716,
      "param": 0,
      "slot": 0,
      "subsystem": "TacticalList",
      "owner_table": "TacticalList",
      "owner_row_id": 21729,
      "ailment_type": 0,
      "status_type": 0,
      "weapon_type": 0,
      "magic_type": 0,
      "equipment": 0,
      "tactical_list_id": 21729,
      "tactical_action_id": 0,
      "enemy_id": 32655,
      "enemy_label": "Rematch_Season20_Boss02_01",
      "enemy_name_best": "Sonzon the Flameguard",
      "enemy_group_id": 0,
      "enemy_group_label": "",
      "enemy_group_enemies": null,
      "skill_id": 0,
      "skill_index": -1,
      "skill_avail_id": 0,
      "skill_condition_list_id": 0,
      "condition_ref_field": "",
      "select_type": -1,
      "turn_count": -1,
      "group_index": -1,
      "friendly_index": -999,
      "priority_skill": -999,
      "co_conditions_in_row": [
        10301,
        10712
      ]
    },
    {
      "condition_id": 716,
      "param": 0,
      "slot": 1,
      "subsystem": "TacticalList",
      "owner_table": "TacticalList",
      "owner_row_id": 123873,
      "ailment_type": 0,
      "status_type": 0,
      "weapon_type": 0,
      "magic_type": 0,
      "equipment": 0,
      "tactical_list_id": 123873,
      "tactical_action_id": 0,
      "enemy_id": 33150,
      "enemy_label": "Enemy_JobTowerThi_f0005_r002EX_002",
      "enemy_name_best": "Trial Great Thief's Henchman",
      "enemy_group_id": 0,
      "enemy_group_label": "",
      "enemy_group_enemies": null,
      "skill_id": 0,
      "skill_index": -1,
      "skill_avail_id": 0,
      "skill_condition_list_id": 0,
      "condition_ref_field": "",
      "select_type": -1,
      "turn_count": -1,
      "group_index": -1,
      "friendly_index": -999,
      "priority_skill": -999,
      "co_conditions_in_row": [
        648,
        10301,
        10712,
        10713
      ]
    },
    {
      "condition_id": 716,
      "param": 0,
      "slot": 1,
      "subsystem": "TacticalList",
      "owner_table": "TacticalList",
      "owner_row_id": 123874,
      "ailment_type": 0,
      "status_type": 0,
      "weapon_type": 0,
      "magic_type": 0,
      "equipment": 0,
      "tactical_list_id": 123874,
      "tactical_action_id": 0,
      "enemy_id": 33150,
      "enemy_label": "Enemy_JobTowerThi_f0005_r002EX_002",
      "enemy_name_best": "Trial Great Thief's Henchman",
      "enemy_group_id": 0,
      "enemy_group_label": "",
      "enemy_group_enemies": null,
      "skill_id": 0,
      "skill_index": -1,
      "skill_avail_id": 0,
      "skill_condition_list_id": 0,
      "condition_ref_field": "",
      "select_type": -1,
      "turn_count": -1,
      "group_index": -1,
      "friendly_index": -999,
      "priority_skill": -999,
      "co_conditions_in_row": [
        648,
        10301,
        10712,
        10713
      ]
    },
    {
      "condition_id": 716,
      "param": 0,
      "slot": 1,
      "subsystem": "TacticalList",
      "owner_table": "TacticalList",
      "owner_row_id": 123875,
      "ailment_type": 0,
      "status_type": 0,
      "weapon_type": 0,
      "magic_type": 0,
      "equipment": 0,
      "tactical_list_id": 123875,
      "tactical_action_id": 0,
      "enemy_id": 33150,
      "enemy_label": "Enemy_JobTowerThi_f0005_r002EX_002",
      "enemy_name_best": "Trial Great Thief's Henchman",
      "enemy_group_id": 0,
      "enemy_group_label": "",
      "enemy_group_enemies": null,
      "skill_id": 0,
      "skill_index": -1,
      "skill_avail_id": 0,
      "skill_condition_list_id": 0,
      "condition_ref_field": "",
      "select_type": -1,
      "turn_count": -1,
      "group_index": -1,
      "friendly_index": -999,
      "priority_skill": -999,
      "co_conditions_in_row": [
        648,
        10301,
        10712,
        10713
      ]
    },
    {
      "condition_id": 716,
      "param": 0,
      "slot": 1,
      "subsystem": "TacticalList",
      "owner_table": "TacticalList",
      "owner_row_id": 123876,
      "ailment_type": 0,
      "status_type": 0,
      "weapon_type": 0,
      "magic_type": 0,
      "equipment": 0,
      "tactical_list_id": 123876,
      "tactical_action_id": 0,
      "enemy_id": 33150,
      "enemy_label": "Enemy_JobTowerThi_f0005_r002EX_002",
      "enemy_name_best": "Trial Great Thief's Henchman",
      "enemy_group_id": 0,
      "enemy_group_label": "",
      "enemy_group_enemies": null,
      "skill_id": 0,
      "skill_index": -1,
      "skill_avail_id": 0,
      "skill_condition_list_id": 0,
      "condition_ref_field": "",
      "select_type": -1,
      "turn_count": -1,
      "group_index": -1,
      "friendly_index": -999,
      "priority_skill": -999,
      "co_conditions_in_row": [
        648,
        10301,
        10712,
        10713
      ]
    },
    {
      "condition_id": 716,
      "param": 0,
      "slot": 1,
      "subsystem": "TacticalList",
      "owner_table": "TacticalList",
      "owner_row_id": 123877,
      "ailment_type": 0,
      "status_type": 0,
      "weapon_type": 0,
      "magic_type": 0,
      "equipment": 0,
      "tactical_list_id": 123877,
      "tactical_action_id": 0,
      "enemy_id": 33150,
      "enemy_label": "Enemy_JobTowerThi_f0005_r002EX_002",
      "enemy_name_best": "Trial Great Thief's Henchman",
      "enemy_group_id": 0,
      "enemy_group_label": "",
      "enemy_group_enemies": null,
      "skill_id": 0,
      "skill_index": -1,
      "skill_avail_id": 0,
      "skill_condition_list_id": 0,
      "condition_ref_field": "",
      "select_type": -1,
      "turn_count": -1,
      "group_index": -1,
      "friendly_index": -999,
      "priority_skill": -999,
      "co_conditions_in_row": [
        648,
        10301,
        10713
      ]
    },
    {
      "condition_id": 716,
      "param": 0,
      "slot": 0,
      "subsystem": "BattleEventList",
      "owner_table": "BattleEventList",
      "owner_row_id": 5,
      "ailment_type": 0,
      "status_type": 0,
      "weapon_type": 0,
      "magic_type": 0,
      "equipment": 0,
      "tactical_list_id": 0,
      "tactical_action_id": 0,
      "enemy_id": 0,
      "enemy_label": "",
      "enemy_name_best": "",
      "enemy_group_id": 19308,
      "enemy_group_label": "AllMaster_Boss_ENG08__B9308",
      "enemy_group_enemies": [
        15047
      ],
      "skill_id": 0,
      "skill_index": -1,
      "skill_avail_id": 0,
      "skill_condition_list_id": 0,
      "condition_ref_field": "",
      "select_type": -1,
      "turn_count": -1,
      "group_index": -1,
      "friendly_index": -999,
      "priority_skill": -999,
      "co_conditions_in_row": []
    }
  ]
}