{
  "condition_id": 10501,
  "total_uses": 15,
  "uses_by_subsystem": {
    "TacticalList": 15
  },
  "uses_by_table": {
    "TacticalList": 15
  },
  "uses_by_subsystem_slot": {
    "TacticalList[2]": 3,
    "TacticalList[0]": 12
  },
  "param_stats": {
    "count": 15,
    "min": 0,
    "max": 0,
    "mean": 0.0,
    "median": 0,
    "p10": 0,
    "p25": 0,
    "p75": 0,
    "p90": 0,
    "top10": [
      [
        0,
        15
      ]
    ]
  },
  "filter_histograms": {
    "ailment_type": [],
    "status_type": [],
    "weapon_type": [],
    "magic_type": [],
    "equipment": []
  },
  "cooccurrence_top": [
    [
      10302,
      10
    ],
    [
      500,
      4
    ],
    [
      10200,
      4
    ],
    [
      1,
      3
    ],
    [
      10100,
      3
    ]
  ],
  "top_enemies": [
    {
      "enemy_id": 31521,
      "use_count": 2,
      "label": "AGM_Boss_Chp0_01_02",
      "name_best": "憤怒する亡者",
      "type_id": 21750,
      "tactical_assign_id": 30195,
      "skills_id": 51203
    },
    {
      "enemy_id": 131521,
      "use_count": 2,
      "label": "AGM_Boss_Chp0_01_02__B31521",
      "name_best": "Ah, yes. It was Navilio who\nintroduced me to Sarisa.",
      "type_id": 121750,
      "tactical_assign_id": 130195,
      "skills_id": 51203
    },
    {
      "enemy_id": 31522,
      "use_count": 2,
      "label": "AGM_Boss_Chp0_01_03",
      "name_best": "絶叫する亡者",
      "type_id": 21765,
      "tactical_assign_id": 30196,
      "skills_id": 51204
    },
    {
      "enemy_id": 131522,
      "use_count": 2,
      "label": "AGM_Boss_Chp0_01_03__B31522",
      "name_best": "I've been shunned by many of my\nbrothers and sisters for my talents\never since I was young...",
      "type_id": 121765,
      "tactical_assign_id": 130196,
      "skills_id": 51204
    },
    {
      "enemy_id": 5113,
      "use_count": 1,
      "label": "B07_003_Boss_01_01",
      "name_best": "巨神像",
      "type_id": 10114,
      "tactical_assign_id": 30150,
      "skills_id": 51108
    },
    {
      "enemy_id": 15113,
      "use_count": 1,
      "label": "B07_003_Boss_01_01__B5113",
      "name_best": "",
      "type_id": 110114,
      "tactical_assign_id": 130150,
      "skills_id": 51108
    },
    {
      "enemy_id": 32736,
      "use_count": 1,
      "label": "Rematch_Season34_Boss01_01",
      "name_best": "",
      "type_id": 110114,
      "tactical_assign_id": 130150,
      "skills_id": 51108
    },
    {
      "enemy_id": 5118,
      "use_count": 1,
      "label": "AGM_Boss_Chp0_01_01",
      "name_best": "悲嘆する亡者",
      "type_id": 21749,
      "tactical_assign_id": 30194,
      "skills_id": 51202
    },
    {
      "enemy_id": 15118,
      "use_count": 1,
      "label": "AGM_Boss_Chp0_01_01__B5118",
      "name_best": "装備者がステータスダウン効果を\n付与するとき、ターン数を１増加する",
      "type_id": 121749,
      "tactical_assign_id": 130194,
      "skills_id": 51202
    },
    {
      "enemy_id": 30536,
      "use_count": 1,
      "label": "ePC0184_ClbBD_Chp4_Em01",
      "name_best": "キングカプカプ",
      "type_id": 20887,
      "tactical_assign_id": 285,
      "skills_id": 20353
    },
    {
      "enemy_id": 30566,
      "use_count": 1,
      "label": "Enemy_ClbBD_Rank03_Zako5K",
      "name_best": "残虐なキングカプカプ",
      "type_id": 5271,
      "tactical_assign_id": 285,
      "skills_id": 20353
    }
  ],
  "top_skills": {},
  "enemy_groups": {},
  "uses_sample": [
    {
      "condition_id": 10501,
      "param": 0,
      "slot": 2,
      "subsystem": "TacticalList",
      "owner_table": "TacticalList",
      "owner_row_id": 21068,
      "ailment_type": 0,
      "status_type": 0,
      "weapon_type": 0,
      "magic_type": 0,
      "equipment": 0,
      "tactical_list_id": 21068,
      "tactical_action_id": 0,
      "enemy_id": 5113,
      "enemy_label": "B07_003_Boss_01_01",
      "enemy_name_best": "巨神像",
      "enemy_group_id": 0,
      "enemy_group_label": "",
      "enemy_group_enemies": null,
      "skill_id": 0,
      "skill_index": -1,
      "skill_avail_id": 0,
      "skill_condition_list_id": 0,
      "condition_ref_field": "",
      "select_type": -1,
      "turn_count": -1,
      "group_index": -1,
      "friendly_index": -999,
      "priority_skill": -999,
      "co_conditions_in_row": [
        1,
        10100
      ]
    },
    {
      "condition_id": 10501,
      "param": 0,
      "slot": 2,
      "subsystem": "TacticalList",
      "owner_table": "TacticalList",
      "owner_row_id": 21068,
      "ailment_type": 0,
      "status_type": 0,
      "weapon_type": 0,
      "magic_type": 0,
      "equipment": 0,
      "tactical_list_id": 21068,
      "tactical_action_id": 0,
      "enemy_id": 15113,
      "enemy_label": "B07_003_Boss_01_01__B5113",
      "enemy_name_best": "",
      "enemy_group_id": 0,
      "enemy_group_label": "",
      "enemy_group_enemies": null,
      "skill_id": 0,
      "skill_index": -1,
      "skill_avail_id": 0,
      "skill_condition_list_id": 0,
      "condition_ref_field": "",
      "select_type": -1,
      "turn_count": -1,
      "group_index": -1,
      "friendly_index": -999,
      "priority_skill": -999,
      "co_conditions_in_row": [
        1,
        10100
      ]
    },
    {
      "condition_id": 10501,
      "param": 0,
      "slot": 2,
      "subsystem": "TacticalList",
      "owner_table": "TacticalList",
      "owner_row_id": 21068,
      "ailment_type": 0,
      "status_type": 0,
      "weapon_type": 0,
      "magic_type": 0,
      "equipment": 0,
      "tactical_list_id": 21068,
      "tactical_action_id": 0,
      "enemy_id": 32736,
      "enemy_label": "Rematch_Season34_Boss01_01",
      "enemy_name_best": "",
      "enemy_group_id": 0,
      "enemy_group_label": "",
      "enemy_group_enemies": null,
      "skill_id": 0,
      "skill_index": -1,
      "skill_avail_id": 0,
      "skill_condition_list_id": 0,
      "condition_ref_field": "",
      "select_type": -1,
      "turn_count": -1,
      "group_index": -1,
      "friendly_index": -999,
      "priority_skill": -999,
      "co_conditions_in_row": [
        1,
        10100
      ]
    },
    {
      "condition_id": 10501,
      "param": 0,
      "slot": 0,
      "subsystem": "TacticalList",
      "owner_table": "TacticalList",
      "owner_row_id": 21262,
      "ailment_type": 0,
      "status_type": 0,
      "weapon_type": 0,
      "magic_type": 0,
      "equipment": 0,
      "tactical_list_id": 21262,
      "tactical_action_id": 0,
      "enemy_id": 5118,
      "enemy_label": "AGM_Boss_Chp0_01_01",
      "enemy_name_best": "悲嘆する亡者",
      "enemy_group_id": 0,
      "enemy_group_label": "",
      "enemy_group_enemies": null,
      "skill_id": 0,
      "skill_index": -1,
      "skill_avail_id": 0,
      "skill_condition_list_id": 0,
      "condition_ref_field": "",
      "select_type": -1,
      "turn_count": -1,
      "group_index": -1,
      "friendly_index": -999,
      "priority_skill": -999,
      "co_conditions_in_row": [
        10302
      ]
    },
    {
      "condition_id": 10501,
      "param": 0,
      "slot": 0,
      "subsystem": "TacticalList",
      "owner_table": "TacticalList",
      "owner_row_id": 21262,
      "ailment_type": 0,
      "status_type": 0,
      "weapon_type": 0,
      "magic_type": 0,
      "equipment": 0,
      "tactical_list_id": 21262,
      "tactical_action_id": 0,
      "enemy_id": 15118,
      "enemy_label": "AGM_Boss_Chp0_01_01__B5118",
      "enemy_name_best": "装備者がステータスダウン効果を\n付与するとき、ターン数を１増加する",
      "enemy_group_id": 0,
      "enemy_group_label": "",
      "enemy_group_enemies": null,
      "skill_id": 0,
      "skill_index": -1,
      "skill_avail_id": 0,
      "skill_condition_list_id": 0,
      "condition_ref_field": "",
      "select_type": -1,
      "turn_count": -1,
      "group_index": -1,
      "friendly_index": -999,
      "priority_skill": -999,
      "co_conditions_in_row": [
        10302
      ]
    },
    {
      "condition_id": 10501,
      "param": 0,
      "slot": 0,
      "subsystem": "TacticalList",
      "owner_table": "TacticalList",
      "owner_row_id": 21271,
      "ailment_type": 0,
      "status_type": 0,
      "weapon_type": 0,
      "magic_type": 0,
      "equipment": 0,
      "tactical_list_id": 21271,
      "tactical_action_id": 0,
      "enemy_id": 31521,
      "enemy_label": "AGM_Boss_Chp0_01_02",
      "enemy_name_best": "憤怒する亡者",
      "enemy_group_id": 0,
      "enemy_group_label": "",
      "enemy_group_enemies": null,
      "skill_id": 0,
      "skill_index": -1,
      "skill_avail_id": 0,
      "skill_condition_list_id": 0,
      "condition_ref_field": "",
      "select_type": -1,
      "turn_count": -1,
      "group_index": -1,
      "friendly_index": -999,
      "priority_skill": -999,
      "co_conditions_in_row": [
        500,
        10302
      ]
    },
    {
      "condition_id": 10501,
      "param": 0,
      "slot": 0,
      "subsystem": "TacticalList",
      "owner_table": "TacticalList",
      "owner_row_id": 21271,
      "ailment_type": 0,
      "status_type": 0,
      "weapon_type": 0,
      "magic_type": 0,
      "equipment": 0,
      "tactical_list_id": 21271,
      "tactical_action_id": 0,
      "enemy_id": 131521,
      "enemy_label": "AGM_Boss_Chp0_01_02__B31521",
      "enemy_name_best": "Ah, yes. It was Navilio who\nintroduced me to Sarisa.",
      "enemy_group_id": 0,
      "enemy_group_label": "",
      "enemy_group_enemies": null,
      "skill_id": 0,
      "skill_index": -1,
      "skill_avail_id": 0,
      "skill_condition_list_id": 0,
      "condition_ref_field": "",
      "select_type": -1,
      "turn_count": -1,
      "group_index": -1,
      "friendly_index": -999,
      "priority_skill": -999,
      "co_conditions_in_row": [
        500,
        10302
      ]
    },
    {
      "condition_id": 10501,
      "param": 0,
      "slot": 0,
      "subsystem": "TacticalList",
      "owner_table": "TacticalList",
      "owner_row_id": 21282,
      "ailment_type": 0,
      "status_type": 0,
      "weapon_type": 0,
      "magic_type": 0,
      "equipment": 0,
      "tactical_list_id": 21282,
      "tactical_action_id": 0,
      "enemy_id": 31521,
      "enemy_label": "AGM_Boss_Chp0_01_02",
      "enemy_name_best": "憤怒する亡者",
      "enemy_group_id": 0,
      "enemy_group_label": "",
      "enemy_group_enemies": null,
      "skill_id": 0,
      "skill_index": -1,
      "skill_avail_id": 0,
      "skill_condition_list_id": 0,
      "condition_ref_field": "",
      "select_type": -1,
      "turn_count": -1,
      "group_index": -1,
      "friendly_index": -999,
      "priority_skill": -999,
      "co_conditions_in_row": [
        10200,
        10302
      ]
    },
    {
      "condition_id": 10501,
      "param": 0,
      "slot": 0,
      "subsystem": "TacticalList",
      "owner_table": "TacticalList",
      "owner_row_id": 21282,
      "ailment_type": 0,
      "status_type": 0,
      "weapon_type": 0,
      "magic_type": 0,
      "equipment": 0,
      "tactical_list_id": 21282,
      "tactical_action_id": 0,
      "enemy_id": 131521,
      "enemy_label": "AGM_Boss_Chp0_01_02__B31521",
      "enemy_name_best": "Ah, yes. It was Navilio who\nintroduced me to Sarisa.",
      "enemy_group_id": 0,
      "enemy_group_label": "",
      "enemy_group_enemies": null,
      "skill_id": 0,
      "skill_index": -1,
      "skill_avail_id": 0,
      "skill_condition_list_id": 0,
      "condition_ref_field": "",
      "select_type": -1,
      "turn_count": -1,
      "group_index": -1,
      "friendly_index": -999,
      "priority_skill": -999,
      "co_conditions_in_row": [
        10200,
        10302
      ]
    },
    {
      "condition_id": 10501,
      "param": 0,
      "slot": 0,
      "subsystem": "TacticalList",
      "owner_table": "TacticalList",
      "owner_row_id": 21283,
      "ailment_type": 0,
      "status_type": 0,
      "weapon_type": 0,
      "magic_type": 0,
      "equipment": 0,
      "tactical_list_id": 21283,
      "tactical_action_id": 0,
      "enemy_id": 31522,
      "enemy_label": "AGM_Boss_Chp0_01_03",
      "enemy_name_best": "絶叫する亡者",
      "enemy_group_id": 0,
      "enemy_group_label": "",
      "enemy_group_enemies": null,
      "skill_id": 0,
      "skill_index": -1,
      "skill_avail_id": 0,
      "skill_condition_list_id": 0,
      "condition_ref_field": "",
      "select_type": -1,
      "turn_count": -1,
      "group_index": -1,
      "friendly_index": -999,
      "priority_skill": -999,
      "co_conditions_in_row": [
        500,
        10302
      ]
    },
    {
      "condition_id": 10501,
      "param": 0,
      "slot": 0,
      "subsystem": "TacticalList",
      "owner_table": "TacticalList",
      "owner_row_id": 21283,
      "ailment_type": 0,
      "status_type": 0,
      "weapon_type": 0,
      "magic_type": 0,
      "equipment": 0,
      "tactical_list_id": 21283,
      "tactical_action_id": 0,
      "enemy_id": 131522,
      "enemy_label": "AGM_Boss_Chp0_01_03__B31522",
      "enemy_name_best": "I've been shunned by many of my\nbrothers and sisters for my talents\never since I was young...",
      "enemy_group_id": 0,
      "enemy_group_label": "",
      "enemy_group_enemies": null,
      "skill_id": 0,
      "skill_index": -1,
      "skill_avail_id": 0,
      "skill_condition_list_id": 0,
      "condition_ref_field": "",
      "select_type": -1,
      "turn_count": -1,
      "group_index": -1,
      "friendly_index": -999,
      "priority_skill": -999,
      "co_conditions_in_row": [
        500,
        10302
      ]
    },
    {
      "condition_id": 10501,
      "param": 0,
      "slot": 0,
      "subsystem": "TacticalList",
      "owner_table": "TacticalList",
      "owner_row_id": 21281,
      "ailment_type": 0,
      "status_type": 0,
      "weapon_type": 0,
      "magic_type": 0,
      "equipment": 0,
      "tactical_list_id": 21281,
      "tactical_action_id": 0,
      "enemy_id": 31522,
      "enemy_label": "AGM_Boss_Chp0_01_03",
      "enemy_name_best": "絶叫する亡者",
      "enemy_group_id": 0,
      "enemy_group_label": "",
      "enemy_group_enemies": null,
      "skill_id": 0,
      "skill_index": -1,
      "skill_avail_id": 0,
      "skill_condition_list_id": 0,
      "condition_ref_field": "",
      "select_type": -1,
      "turn_count": -1,
      "group_index": -1,
      "friendly_index": -999,
      "priority_skill": -999,
      "co_conditions_in_row": [
        10200,
        10302
      ]
    },
    {
      "condition_id": 10501,
      "param": 0,
      "slot": 0,
      "subsystem": "TacticalList",
      "owner_table": "TacticalList",
      "owner_row_id": 21281,
      "ailment_type": 0,
      "status_type": 0,
      "weapon_type": 0,
      "magic_type": 0,
      "equipment": 0,
      "tactical_list_id": 21281,
      "tactical_action_id": 0,
      "enemy_id": 131522,
      "enemy_label": "AGM_Boss_Chp0_01_03__B31522",
      "enemy_name_best": "I've been shunned by many of my\nbrothers and sisters for my talents\never since I was young...",
      "enemy_group_id": 0,
      "enemy_group_label": "",
      "enemy_group_enemies": null,
      "skill_id": 0,
      "skill_index": -1,
      "skill_avail_id": 0,
      "skill_condition_list_id": 0,
      "condition_ref_field": "",
      "select_type": -1,
      "turn_count": -1,
      "group_index": -1,
      "friendly_index": -999,
      "priority_skill": -999,
      "co_conditions_in_row": [
        10200,
        10302
      ]
    },
    {
      "condition_id": 10501,
      "param": 0,
      "slot": 0,
      "subsystem": "TacticalList",
      "owner_table": "TacticalList",
      "owner_row_id": 1683,
      "ailment_type": 0,
      "status_type": 0,
      "weapon_type": 0,
      "magic_type": 0,
      "equipment": 0,
      "tactical_list_id": 1683,
      "tactical_action_id": 0,
      "enemy_id": 30536,
      "enemy_label": "ePC0184_ClbBD_Chp4_Em01",
      "enemy_name_best": "キングカプカプ",
      "enemy_group_id": 0,
      "enemy_group_label": "",
      "enemy_group_enemies": null,
      "skill_id": 0,
      "skill_index": -1,
      "skill_avail_id": 0,
      "skill_condition_list_id": 0,
      "condition_ref_field": "",
      "select_type": -1,
      "turn_count": -1,
      "group_index": -1,
      "friendly_index": -999,
      "priority_skill": -999,
      "co_conditions_in_row": []
    },
    {
      "condition_id": 10501,
      "param": 0,
      "slot": 0,
      "subsystem": "TacticalList",
      "owner_table": "TacticalList",
      "owner_row_id": 1683,
      "ailment_type": 0,
      "status_type": 0,
      "weapon_type": 0,
      "magic_type": 0,
      "equipment": 0,
      "tactical_list_id": 1683,
      "tactical_action_id": 0,
      "enemy_id": 30566,
      "enemy_label": "Enemy_ClbBD_Rank03_Zako5K",
      "enemy_name_best": "残虐なキングカプカプ",
      "enemy_group_id": 0,
      "enemy_group_label": "",
      "enemy_group_enemies": null,
      "skill_id": 0,
      "skill_index": -1,
      "skill_avail_id": 0,
      "skill_condition_list_id": 0,
      "condition_ref_field": "",
      "select_type": -1,
      "turn_count": -1,
      "group_index": -1,
      "friendly_index": -999,
      "priority_skill": -999,
      "co_conditions_in_row": []
    }
  ]
}